{
"meta":{"test_sets":[],"test_metrics":[],"learn_metrics":[{"best_value":"Min","name":"RMSE"}],"launch_mode":"Train","parameters":"","iteration_count":1000,"learn_sets":["learn"],"name":"experiment"},
"iterations":[
{"learn":[14.61268541],"iteration":0,"passed_time":0.2116883741,"remaining_time":211.4766857},
{"learn":[14.23196558],"iteration":1,"passed_time":0.213497758,"remaining_time":106.5353813},
{"learn":[13.86674177],"iteration":2,"passed_time":0.2178628272,"remaining_time":72.40307957},
{"learn":[13.49946468],"iteration":3,"passed_time":0.2235562073,"remaining_time":55.66549561},
{"learn":[13.16661202],"iteration":4,"passed_time":0.2248289377,"remaining_time":44.7409586},
{"learn":[12.85632158],"iteration":5,"passed_time":0.2259682773,"remaining_time":37.43541127},
{"learn":[12.56784336],"iteration":6,"passed_time":0.2271598216,"remaining_time":32.22424326},
{"learn":[12.31617801],"iteration":7,"passed_time":0.2280457047,"remaining_time":28.27766738},
{"learn":[12.01509946],"iteration":8,"passed_time":0.2301557022,"remaining_time":25.3427001},
{"learn":[11.71512571],"iteration":9,"passed_time":0.2326506761,"remaining_time":23.03241693},
{"learn":[11.43264457],"iteration":10,"passed_time":0.234356385,"remaining_time":21.07076952},
{"learn":[11.17973129],"iteration":11,"passed_time":0.235700255,"remaining_time":19.40598766},
{"learn":[10.93746433],"iteration":12,"passed_time":0.2367283431,"remaining_time":17.9731442},
{"learn":[10.69387075],"iteration":13,"passed_time":0.2379696898,"remaining_time":16.75986529},
{"learn":[10.4615922],"iteration":14,"passed_time":0.2393306442,"remaining_time":15.71604563},
{"learn":[10.2299235],"iteration":15,"passed_time":0.2402529984,"remaining_time":14.7755594},
{"learn":[10.01419731],"iteration":16,"passed_time":0.2411156589,"remaining_time":13.9421584},
{"learn":[9.795856918],"iteration":17,"passed_time":0.2447440336,"remaining_time":13.35214672},
{"learn":[9.60040151],"iteration":18,"passed_time":0.2827659343,"remaining_time":14.59965166},
{"learn":[9.418664989],"iteration":19,"passed_time":0.2854679958,"remaining_time":13.98793179},
{"learn":[9.249278645],"iteration":20,"passed_time":0.2870118585,"remaining_time":13.3802195},
{"learn":[9.090113396],"iteration":21,"passed_time":0.2939941254,"remaining_time":13.06937521},
{"learn":[8.909548708],"iteration":22,"passed_time":0.2960623401,"remaining_time":12.57621332},
{"learn":[8.740140208],"iteration":23,"passed_time":0.2979254039,"remaining_time":12.11563309},
{"learn":[8.59377682],"iteration":24,"passed_time":0.3009431935,"remaining_time":11.73678455},
{"learn":[8.453885414],"iteration":25,"passed_time":0.302234527,"remaining_time":11.32217036},
{"learn":[8.317732234],"iteration":26,"passed_time":0.3041443069,"remaining_time":10.96045965},
{"learn":[8.180896085],"iteration":27,"passed_time":0.3082111638,"remaining_time":10.6993304},
{"learn":[8.053220863],"iteration":28,"passed_time":0.3105121869,"remaining_time":10.3968046},
{"learn":[7.924234474],"iteration":29,"passed_time":0.3126302063,"remaining_time":10.10837667},
{"learn":[7.818879511],"iteration":30,"passed_time":0.3145935544,"remaining_time":9.833585619},
{"learn":[7.719346395],"iteration":31,"passed_time":0.3158675181,"remaining_time":9.554992422},
{"learn":[7.624163594],"iteration":32,"passed_time":0.3175938459,"remaining_time":9.306462091},
{"learn":[7.524952543],"iteration":33,"passed_time":0.3190688221,"remaining_time":9.065308298},
{"learn":[7.424464745],"iteration":34,"passed_time":0.3494852212,"remaining_time":9.635806814},
{"learn":[7.327482321],"iteration":35,"passed_time":0.3557658063,"remaining_time":9.526617703},
{"learn":[7.238666841],"iteration":36,"passed_time":0.3584331438,"remaining_time":9.328949122},
{"learn":[7.158842395],"iteration":37,"passed_time":0.3602991744,"remaining_time":9.121258047},
{"learn":[7.074348246],"iteration":38,"passed_time":0.3721879912,"remaining_time":9.171093834},
{"learn":[6.992269093],"iteration":39,"passed_time":0.3779025561,"remaining_time":9.069661347},
{"learn":[6.925219745],"iteration":40,"passed_time":0.3855065803,"remaining_time":9.01709294},
{"learn":[6.86013671],"iteration":41,"passed_time":0.388179545,"remaining_time":8.854190574},
{"learn":[6.786739622],"iteration":42,"passed_time":0.3894838815,"remaining_time":8.668280805},
{"learn":[6.73057926],"iteration":43,"passed_time":0.391256242,"remaining_time":8.500931076},
{"learn":[6.666356486],"iteration":44,"passed_time":0.3923955746,"remaining_time":8.327506082},
{"learn":[6.606182832],"iteration":45,"passed_time":0.393746253,"remaining_time":8.1659549},
{"learn":[6.547854615],"iteration":46,"passed_time":0.3948511691,"remaining_time":8.006237534},
{"learn":[6.49240675],"iteration":47,"passed_time":0.396355485,"remaining_time":7.861050453},
{"learn":[6.431317261],"iteration":48,"passed_time":0.4006251225,"remaining_time":7.775397786},
{"learn":[6.377586395],"iteration":49,"passed_time":0.4017230343,"remaining_time":7.632737652},
{"learn":[6.327558015],"iteration":50,"passed_time":0.4030714332,"remaining_time":7.500290002},
{"learn":[6.282040317],"iteration":51,"passed_time":0.4042509931,"remaining_time":7.369806567},
{"learn":[6.237655841],"iteration":52,"passed_time":0.4052909314,"remaining_time":7.241707774},
{"learn":[6.192792003],"iteration":53,"passed_time":0.406479958,"remaining_time":7.120926671},
{"learn":[6.150579347],"iteration":54,"passed_time":0.4074862292,"remaining_time":7.001354302},
{"learn":[6.115693845],"iteration":55,"passed_time":0.4085319853,"remaining_time":6.886682038},
{"learn":[6.078780782],"iteration":56,"passed_time":0.4108869364,"remaining_time":6.797655808},
{"learn":[6.045146957],"iteration":57,"passed_time":0.4138079767,"remaining_time":6.720812311},
{"learn":[6.008080327],"iteration":58,"passed_time":0.4150674334,"remaining_time":6.619973811},
{"learn":[5.977575734],"iteration":59,"passed_time":0.4163211646,"remaining_time":6.522364912},
{"learn":[5.948036502],"iteration":60,"passed_time":0.4182303144,"remaining_time":6.438004349},
{"learn":[5.914888282],"iteration":61,"passed_time":0.4215714322,"remaining_time":6.377967797},
{"learn":[5.884957796],"iteration":62,"passed_time":0.4228907181,"remaining_time":6.289660362},
{"learn":[5.849539885],"iteration":63,"passed_time":0.4238910152,"remaining_time":6.199406097},
{"learn":[5.821387627],"iteration":64,"passed_time":0.4252613422,"remaining_time":6.117220846},
{"learn":[5.797012279],"iteration":65,"passed_time":0.4262333234,"remaining_time":6.031847335},
{"learn":[5.768685095],"iteration":66,"passed_time":0.4272898204,"remaining_time":5.950170185},
{"learn":[5.755484587],"iteration":67,"passed_time":0.4277863829,"remaining_time":5.863189837},
{"learn":[5.731887055],"iteration":68,"passed_time":0.4294141106,"remaining_time":5.793978797},
{"learn":[5.707148487],"iteration":69,"passed_time":0.4304279318,"remaining_time":5.718542522},
{"learn":[5.685365039],"iteration":70,"passed_time":0.4314653826,"remaining_time":5.645511837},
{"learn":[5.663541834],"iteration":71,"passed_time":0.4364348481,"remaining_time":5.625160265},
{"learn":[5.638108797],"iteration":72,"passed_time":0.4376574849,"remaining_time":5.557650528},
{"learn":[5.619204893],"iteration":73,"passed_time":0.4413939961,"remaining_time":5.523389735},
{"learn":[5.598472793],"iteration":74,"passed_time":0.4433628265,"remaining_time":5.468141527},
{"learn":[5.577007075],"iteration":75,"passed_time":0.4444653103,"remaining_time":5.403762457},
{"learn":[5.562637084],"iteration":76,"passed_time":0.4454297147,"remaining_time":5.339371775},
{"learn":[5.54729991],"iteration":77,"passed_time":0.4466851282,"remaining_time":5.280047284},
{"learn":[5.530737623],"iteration":78,"passed_time":0.4526578956,"remaining_time":5.277188884},
{"learn":[5.513704873],"iteration":79,"passed_time":0.4558552536,"remaining_time":5.242335417},
{"learn":[5.501575529],"iteration":80,"passed_time":0.4570848066,"remaining_time":5.185937497},
{"learn":[5.484080734],"iteration":81,"passed_time":0.4589818758,"remaining_time":5.138358073},
{"learn":[5.472178894],"iteration":82,"passed_time":0.4600669449,"remaining_time":5.082908295},
{"learn":[5.458923342],"iteration":83,"passed_time":0.4611096966,"remaining_time":5.028291453},
{"learn":[5.451382371],"iteration":84,"passed_time":0.4622229747,"remaining_time":4.975694375},
{"learn":[5.441410748],"iteration":85,"passed_time":0.4698005068,"remaining_time":4.992996084},
{"learn":[5.434047468],"iteration":86,"passed_time":0.4710359646,"remaining_time":4.943170525},
{"learn":[5.422107497],"iteration":87,"passed_time":0.4728987449,"remaining_time":4.900950629},
{"learn":[5.40731265],"iteration":88,"passed_time":0.4741087451,"remaining_time":4.852955806},
{"learn":[5.396360181],"iteration":89,"passed_time":0.4751656741,"remaining_time":4.804452927},
{"learn":[5.383793239],"iteration":90,"passed_time":0.4763780858,"remaining_time":4.758545934},
{"learn":[5.369605034],"iteration":91,"passed_time":0.4775873538,"remaining_time":4.713579536},
{"learn":[5.357467333],"iteration":92,"passed_time":0.4786451212,"remaining_time":4.668076612},
{"learn":[5.341109968],"iteration":93,"passed_time":0.4855192446,"remaining_time":4.679579103},
{"learn":[5.330529276],"iteration":94,"passed_time":0.4867617203,"remaining_time":4.637045861},
{"learn":[5.319862075],"iteration":95,"passed_time":0.4879760381,"remaining_time":4.595107692},
{"learn":[5.313052243],"iteration":96,"passed_time":0.488920506,"remaining_time":4.551497081},
{"learn":[5.299677207],"iteration":97,"passed_time":0.4898508758,"remaining_time":4.508627449},
{"learn":[5.287546698],"iteration":98,"passed_time":0.4908846272,"remaining_time":4.46754595},
{"learn":[5.279803754],"iteration":99,"passed_time":0.4919849417,"remaining_time":4.427864475},
{"learn":[5.272254612],"iteration":100,"passed_time":0.4935229228,"remaining_time":4.392842649},
{"learn":[5.268813888],"iteration":101,"passed_time":0.4961740039,"remaining_time":4.368277015},
{"learn":[5.258113767],"iteration":102,"passed_time":0.4974568993,"remaining_time":4.332221735},
{"learn":[5.251018576],"iteration":103,"passed_time":0.4989834797,"remaining_time":4.298934594},
{"learn":[5.24171237],"iteration":104,"passed_time":0.5005702453,"remaining_time":4.266765424},
{"learn":[5.233984943],"iteration":105,"passed_time":0.501589207,"remaining_time":4.230384444},
{"learn":[5.226240449],"iteration":106,"passed_time":0.5024679217,"remaining_time":4.193493964},
{"learn":[5.220541644],"iteration":107,"passed_time":0.503490588,"remaining_time":4.158459301},
{"learn":[5.211712096],"iteration":108,"passed_time":0.5045415137,"remaining_time":4.124279713},
{"learn":[5.203388597],"iteration":109,"passed_time":0.5103862782,"remaining_time":4.129488978},
{"learn":[5.196026544],"iteration":110,"passed_time":0.5120578795,"remaining_time":4.10107617},
{"learn":[5.188716772],"iteration":111,"passed_time":0.5132746388,"remaining_time":4.069534636},
{"learn":[5.182163132],"iteration":112,"passed_time":0.5143192029,"remaining_time":4.037178168},
{"learn":[5.17764747],"iteration":113,"passed_time":0.51530947,"remaining_time":4.004949039},
{"learn":[5.170548056],"iteration":114,"passed_time":0.5161812425,"remaining_time":3.972351301},
{"learn":[5.165901827],"iteration":115,"passed_time":0.5169135383,"remaining_time":3.939237654},
{"learn":[5.160333668],"iteration":116,"passed_time":0.5178563349,"remaining_time":3.908266186},
{"learn":[5.148953243],"iteration":117,"passed_time":0.5191319322,"remaining_time":3.880291222},
{"learn":[5.144729126],"iteration":118,"passed_time":0.5206918975,"remaining_time":3.854870267},
{"learn":[5.139939946],"iteration":119,"passed_time":0.5233780216,"remaining_time":3.838105492},
{"learn":[5.132898872],"iteration":120,"passed_time":0.5246868269,"remaining_time":3.811567941},
{"learn":[5.129073077],"iteration":121,"passed_time":0.5256957888,"remaining_time":3.783286087},
{"learn":[5.127123916],"iteration":122,"passed_time":0.5261872522,"remaining_time":3.751757887},
{"learn":[5.121282057],"iteration":123,"passed_time":0.5269917231,"remaining_time":3.722941528},
{"learn":[5.114489821],"iteration":124,"passed_time":0.5278961233,"remaining_time":3.695272863},
{"learn":[5.107777291],"iteration":125,"passed_time":0.5287319175,"remaining_time":3.667553142},
{"learn":[5.103518754],"iteration":126,"passed_time":0.5296278387,"remaining_time":3.640670104},
{"learn":[5.101133351],"iteration":127,"passed_time":0.530242793,"remaining_time":3.612279027},
{"learn":[5.096462705],"iteration":128,"passed_time":0.5310994019,"remaining_time":3.585950226},
{"learn":[5.08562082],"iteration":129,"passed_time":0.5319482969,"remaining_time":3.559961679},
{"learn":[5.080483682],"iteration":130,"passed_time":0.5348029746,"remaining_time":3.547662481},
{"learn":[5.07437499],"iteration":131,"passed_time":0.5378029952,"remaining_time":3.53646212},
{"learn":[5.070683732],"iteration":132,"passed_time":0.5391962182,"remaining_time":3.514910686},
{"learn":[5.06432037],"iteration":133,"passed_time":0.5402566663,"remaining_time":3.4915095},
{"learn":[5.057436484],"iteration":134,"passed_time":0.5411366995,"remaining_time":3.467283297},
{"learn":[5.053254656],"iteration":135,"passed_time":0.5419499185,"remaining_time":3.442975953},
{"learn":[5.04801663],"iteration":136,"passed_time":0.5431364981,"remaining_time":3.421363488},
{"learn":[5.045680836],"iteration":137,"passed_time":0.5440363418,"remaining_time":3.39825599},
{"learn":[5.041857933],"iteration":138,"passed_time":0.544876878,"remaining_time":3.375100661},
{"learn":[5.035264888],"iteration":139,"passed_time":0.5456951454,"remaining_time":3.352127321},
{"learn":[5.028771948],"iteration":140,"passed_time":0.5465063606,"remaining_time":3.329425275},
{"learn":[5.024912247],"iteration":141,"passed_time":0.548735432,"remaining_time":3.315598596},
{"learn":[5.02239068],"iteration":142,"passed_time":0.5513948081,"remaining_time":3.304512941},
{"learn":[5.017110572],"iteration":143,"passed_time":0.5530401887,"remaining_time":3.287516677},
{"learn":[5.010707886],"iteration":144,"passed_time":0.5540922338,"remaining_time":3.267233517},
{"learn":[5.004389868],"iteration":145,"passed_time":0.554894629,"remaining_time":3.245753515},
{"learn":[4.997628683],"iteration":146,"passed_time":0.555714303,"remaining_time":3.224655105},
{"learn":[4.991497851],"iteration":147,"passed_time":0.5567851225,"remaining_time":3.205276516},
{"learn":[4.988345253],"iteration":148,"passed_time":0.558876061,"remaining_time":3.191969986},
{"learn":[4.98460423],"iteration":149,"passed_time":0.5720437059,"remaining_time":3.241581},
{"learn":[4.982441783],"iteration":150,"passed_time":0.573240648,"remaining_time":3.223055034},
{"learn":[4.977461771],"iteration":151,"passed_time":0.5742538325,"remaining_time":3.203731908},
{"learn":[4.973601586],"iteration":152,"passed_time":0.5753307924,"remaining_time":3.185001184},
{"learn":[4.968328804],"iteration":153,"passed_time":0.5814802916,"remaining_time":3.194365758},
{"learn":[4.9640736],"iteration":154,"passed_time":0.5833285296,"remaining_time":3.180081339},
{"learn":[4.960865882],"iteration":155,"passed_time":0.584660347,"remaining_time":3.16316239},
{"learn":[4.957014156],"iteration":156,"passed_time":0.5857609848,"remaining_time":3.145200702},
{"learn":[4.952244852],"iteration":157,"passed_time":0.5868792778,"remaining_time":3.127546531},
{"learn":[4.949695675],"iteration":158,"passed_time":0.5881531036,"remaining_time":3.11092302},
{"learn":[4.946584698],"iteration":159,"passed_time":0.5891708077,"remaining_time":3.09314674},
{"learn":[4.940192834],"iteration":160,"passed_time":0.5900465601,"remaining_time":3.074838906},
{"learn":[4.936727994],"iteration":161,"passed_time":0.5908274114,"remaining_time":3.056255375},
{"learn":[4.932342063],"iteration":162,"passed_time":0.595623046,"remaining_time":3.05850607},
{"learn":[4.925830838],"iteration":163,"passed_time":0.5969136421,"remaining_time":3.042803688},
{"learn":[4.922571773],"iteration":164,"passed_time":0.5980758293,"remaining_time":3.026626166},
{"learn":[4.918395814],"iteration":165,"passed_time":0.599283673,"remaining_time":3.010858936},
{"learn":[4.911142452],"iteration":166,"passed_time":0.6003657635,"remaining_time":2.994638809},
{"learn":[4.908276131],"iteration":167,"passed_time":0.6012849051,"remaining_time":2.977791911},
{"learn":[4.904584645],"iteration":168,"passed_time":0.6021178796,"remaining_time":2.960709811},
{"learn":[4.89795517],"iteration":169,"passed_time":0.6029258151,"remaining_time":2.943696627},
{"learn":[4.895556491],"iteration":170,"passed_time":0.6037575859,"remaining_time":2.92698853},
{"learn":[4.890591233],"iteration":171,"passed_time":0.6045766249,"remaining_time":2.910403752},
{"learn":[4.884629277],"iteration":172,"passed_time":0.6053792708,"remaining_time":2.893922873},
{"learn":[4.880550786],"iteration":173,"passed_time":0.610381033,"remaining_time":2.897555938},
{"learn":[4.876384842],"iteration":174,"passed_time":0.6117983033,"remaining_time":2.884192001},
{"learn":[4.872638238],"iteration":175,"passed_time":0.6133453994,"remaining_time":2.871571643},
{"learn":[4.869137118],"iteration":176,"passed_time":0.6141888523,"remaining_time":2.855804663},
{"learn":[4.863587157],"iteration":177,"passed_time":0.6150767793,"remaining_time":2.840410745},
{"learn":[4.858028614],"iteration":178,"passed_time":0.6159121901,"remaining_time":2.824938034},
{"learn":[4.853838176],"iteration":179,"passed_time":0.6167188827,"remaining_time":2.809497132},
{"learn":[4.853462329],"iteration":180,"passed_time":0.6171192463,"remaining_time":2.792379352},
{"learn":[4.851573196],"iteration":181,"passed_time":0.6179190763,"remaining_time":2.777240684},
{"learn":[4.848442087],"iteration":182,"passed_time":0.6187947837,"remaining_time":2.762597477},
{"learn":[4.845547104],"iteration":183,"passed_time":0.6196576743,"remaining_time":2.748047077},
{"learn":[4.839868817],"iteration":184,"passed_time":0.6204543582,"remaining_time":2.733352984},
{"learn":[4.836336958],"iteration":185,"passed_time":0.6239048218,"remaining_time":2.730422177},
{"learn":[4.831124789],"iteration":186,"passed_time":0.6263833933,"remaining_time":2.723260421},
{"learn":[4.827407333],"iteration":187,"passed_time":0.6279328349,"remaining_time":2.712135436},
{"learn":[4.824088918],"iteration":188,"passed_time":0.6288424918,"remaining_time":2.698366459},
{"learn":[4.820934539],"iteration":189,"passed_time":0.6297391839,"remaining_time":2.684677573},
{"learn":[4.816975227],"iteration":190,"passed_time":0.6306156346,"remaining_time":2.671036902},
{"learn":[4.812340486],"iteration":191,"passed_time":0.6314499614,"remaining_time":2.657351921},
{"learn":[4.806402747],"iteration":192,"passed_time":0.6322454675,"remaining_time":2.643637784},
{"learn":[4.801521788],"iteration":193,"passed_time":0.6330648837,"remaining_time":2.630156166},
{"learn":[4.797601172],"iteration":194,"passed_time":0.6338722222,"remaining_time":2.616754558},
{"learn":[4.792694629],"iteration":195,"passed_time":0.6347241481,"remaining_time":2.603664363},
{"learn":[4.789794613],"iteration":196,"passed_time":0.6355213881,"remaining_time":2.590475506},
{"learn":[4.785367055],"iteration":197,"passed_time":0.6390409125,"remaining_time":2.588438444},
{"learn":[4.780376856],"iteration":198,"passed_time":0.6413264178,"remaining_time":2.5814194},
{"learn":[4.776691261],"iteration":199,"passed_time":0.6427050612,"remaining_time":2.570820245},
{"learn":[4.773470753],"iteration":200,"passed_time":0.6437754903,"remaining_time":2.559087646},
{"learn":[4.77207327],"iteration":201,"passed_time":0.6447023307,"remaining_time":2.546893366},
{"learn":[4.767347177],"iteration":202,"passed_time":0.6455246238,"remaining_time":2.534399631},
{"learn":[4.763983068],"iteration":203,"passed_time":0.6463075216,"remaining_time":2.521866604},
{"learn":[4.761588849],"iteration":204,"passed_time":0.6470955677,"remaining_time":2.509468177},
{"learn":[4.758558086],"iteration":205,"passed_time":0.6478888192,"remaining_time":2.497202536},
{"learn":[4.753678804],"iteration":206,"passed_time":0.6487764078,"remaining_time":2.485409137},
{"learn":[4.746510889],"iteration":207,"passed_time":0.649717381,"remaining_time":2.473923874},
{"learn":[4.744840601],"iteration":208,"passed_time":0.6507896365,"remaining_time":2.463036375},
{"learn":[4.741702222],"iteration":209,"passed_time":0.6553798514,"remaining_time":2.465476584},
{"learn":[4.739352853],"iteration":210,"passed_time":0.6569404707,"remaining_time":2.456521476},
{"learn":[4.735539287],"iteration":211,"passed_time":0.6584962437,"remaining_time":2.447618113},
{"learn":[4.730726751],"iteration":212,"passed_time":0.6596173209,"remaining_time":2.437177613},
{"learn":[4.726416092],"iteration":213,"passed_time":0.6607764728,"remaining_time":2.426964054},
{"learn":[4.721293082],"iteration":214,"passed_time":0.6621758417,"remaining_time":2.417711794},
{"learn":[4.718443695],"iteration":215,"passed_time":0.6635076259,"remaining_time":2.408286939},
{"learn":[4.711627962],"iteration":216,"passed_time":0.6705197311,"remaining_time":2.419432947},
{"learn":[4.709790764],"iteration":217,"passed_time":0.6729054827,"remaining_time":2.413816915},
{"learn":[4.706913073],"iteration":218,"passed_time":0.6742955678,"remaining_time":2.404679628},
{"learn":[4.703846389],"iteration":219,"passed_time":0.6752931234,"remaining_time":2.394221074},
{"learn":[4.701001135],"iteration":220,"passed_time":0.6762481607,"remaining_time":2.383698268},
{"learn":[4.700380864],"iteration":221,"passed_time":0.677301463,"remaining_time":2.373606028},
{"learn":[4.695837486],"iteration":222,"passed_time":0.678316614,"remaining_time":2.363461924},
{"learn":[4.691242996],"iteration":223,"passed_time":0.6793625101,"remaining_time":2.353505839},
{"learn":[4.690284609],"iteration":224,"passed_time":0.6806511644,"remaining_time":2.344465122},
{"learn":[4.68827119],"iteration":225,"passed_time":0.6835973687,"remaining_time":2.341169749},
{"learn":[4.686922425],"iteration":226,"passed_time":0.6850913405,"remaining_time":2.332932186},
{"learn":[4.686085874],"iteration":227,"passed_time":0.6861031973,"remaining_time":2.323121352},
{"learn":[4.683230741],"iteration":228,"passed_time":0.6871105326,"remaining_time":2.313372143},
{"learn":[4.6773487],"iteration":229,"passed_time":0.6881272553,"remaining_time":2.303730376},
{"learn":[4.671462906],"iteration":230,"passed_time":0.6893474842,"remaining_time":2.294840759},
{"learn":[4.664799601],"iteration":231,"passed_time":0.690306396,"remaining_time":2.285152207},
{"learn":[4.660979386],"iteration":232,"passed_time":0.6913167519,"remaining_time":2.275707934},
{"learn":[4.656281279],"iteration":233,"passed_time":0.6923475428,"remaining_time":2.26640264},
{"learn":[4.651997094],"iteration":234,"passed_time":0.6973596797,"remaining_time":2.270128319},
{"learn":[4.650151977],"iteration":235,"passed_time":0.6999804072,"remaining_time":2.266038267},
{"learn":[4.648478046],"iteration":236,"passed_time":0.7015103742,"remaining_time":2.258449011},
{"learn":[4.646364602],"iteration":237,"passed_time":0.702827278,"remaining_time":2.250228512},
{"learn":[4.642635873],"iteration":238,"passed_time":0.7040956064,"remaining_time":2.241911115},
{"learn":[4.640860821],"iteration":239,"passed_time":0.70529962,"remaining_time":2.233448797},
{"learn":[4.639446822],"iteration":240,"passed_time":0.7062025026,"remaining_time":2.224098338},
{"learn":[4.637120072],"iteration":241,"passed_time":0.7070255061,"remaining_time":2.214567494},
{"learn":[4.633769267],"iteration":242,"passed_time":0.7092239337,"remaining_time":2.209393077},
{"learn":[4.630491517],"iteration":243,"passed_time":0.7116267826,"remaining_time":2.204876425},
{"learn":[4.627813333],"iteration":244,"passed_time":0.7130649735,"remaining_time":2.197404306},
{"learn":[4.622496304],"iteration":245,"passed_time":0.7141461843,"remaining_time":2.188887085},
{"learn":[4.618979301],"iteration":246,"passed_time":0.7150113035,"remaining_time":2.179771302},
{"learn":[4.616563458],"iteration":247,"passed_time":0.7158194189,"remaining_time":2.170549206},
{"learn":[4.614759385],"iteration":248,"passed_time":0.7166893513,"remaining_time":2.161581136},
{"learn":[4.61251363],"iteration":249,"passed_time":0.717481788,"remaining_time":2.152445364},
{"learn":[4.608796693],"iteration":250,"passed_time":0.718354025,"remaining_time":2.143614202},
{"learn":[4.60847774],"iteration":251,"passed_time":0.7192703023,"remaining_time":2.134976929},
{"learn":[4.605195659],"iteration":252,"passed_time":0.7200835682,"remaining_time":2.126096543},
{"learn":[4.60103766],"iteration":253,"passed_time":0.7209367863,"remaining_time":2.117397018},
{"learn":[4.599325598],"iteration":254,"passed_time":0.7217001613,"remaining_time":2.10849655},
{"learn":[4.597012808],"iteration":255,"passed_time":0.7280790461,"remaining_time":2.115979728},
{"learn":[4.594161533],"iteration":256,"passed_time":0.7297912331,"remaining_time":2.10986337},
{"learn":[4.592197259],"iteration":257,"passed_time":0.7306713404,"remaining_time":2.101388118},
{"learn":[4.58952828],"iteration":258,"passed_time":0.7314704333,"remaining_time":2.092739734},
{"learn":[4.585816572],"iteration":259,"passed_time":0.7322955214,"remaining_time":2.084225715},
{"learn":[4.582934052],"iteration":260,"passed_time":0.7331363193,"remaining_time":2.075815096},
{"learn":[4.582234842],"iteration":261,"passed_time":0.7339407774,"remaining_time":2.0673599},
{"learn":[4.57571562],"iteration":262,"passed_time":0.7347501529,"remaining_time":2.058976664},
{"learn":[4.571197349],"iteration":263,"passed_time":0.735575958,"remaining_time":2.05069661},
{"learn":[4.56723703],"iteration":264,"passed_time":0.7365787227,"remaining_time":2.042963627},
{"learn":[4.560335567],"iteration":265,"passed_time":0.7397722331,"remaining_time":2.041326388},
{"learn":[4.554709345],"iteration":266,"passed_time":0.7424223896,"remaining_time":2.038185811},
{"learn":[4.552806306],"iteration":267,"passed_time":0.7436218138,"remaining_time":2.031086447},
{"learn":[4.550766241],"iteration":268,"passed_time":0.7446152365,"remaining_time":2.023471144},
{"learn":[4.549216045],"iteration":269,"passed_time":0.7454290572,"remaining_time":2.015419303},
{"learn":[4.547687452],"iteration":270,"passed_time":0.7462575467,"remaining_time":2.007460338},
{"learn":[4.545642435],"iteration":271,"passed_time":0.7470516514,"remaining_time":1.999461773},
{"learn":[4.543930359],"iteration":272,"passed_time":0.7478373991,"remaining_time":1.991493733},
{"learn":[4.541029943],"iteration":273,"passed_time":0.74870255,"remaining_time":1.983788508},
{"learn":[4.537781449],"iteration":274,"passed_time":0.749542802,"remaining_time":1.976067387},
{"learn":[4.53066128],"iteration":275,"passed_time":0.7503524573,"remaining_time":1.968315866},
{"learn":[4.526763956],"iteration":276,"passed_time":0.7516399019,"remaining_time":1.961861549},
{"learn":[4.522036004],"iteration":277,"passed_time":0.7557611907,"remaining_time":1.962804243},
{"learn":[4.515307629],"iteration":278,"passed_time":0.7571794155,"remaining_time":1.9567253},
{"learn":[4.51109143],"iteration":279,"passed_time":0.758483988,"remaining_time":1.950387398},
{"learn":[4.508233494],"iteration":280,"passed_time":0.7594170496,"remaining_time":1.943134728},
{"learn":[4.502555629],"iteration":281,"passed_time":0.7602624904,"remaining_time":1.935703788},
{"learn":[4.500081355],"iteration":282,"passed_time":0.7611221483,"remaining_time":1.928355408},
{"learn":[4.495281743],"iteration":283,"passed_time":0.7619835678,"remaining_time":1.921057164},
{"learn":[4.492138869],"iteration":284,"passed_time":0.7627570948,"remaining_time":1.913583589},
{"learn":[4.491708261],"iteration":285,"passed_time":0.7637626866,"remaining_time":1.906736218},
{"learn":[4.489398865],"iteration":286,"passed_time":0.7646110931,"remaining_time":1.899539057},
{"learn":[4.485796373],"iteration":287,"passed_time":0.7654962045,"remaining_time":1.892476728},
{"learn":[4.479542205],"iteration":288,"passed_time":0.7663616154,"remaining_time":1.88540868},
{"learn":[4.475986993],"iteration":289,"passed_time":0.7697446597,"remaining_time":1.88454727},
{"learn":[4.468661855],"iteration":290,"passed_time":0.771740891,"remaining_time":1.880289662},
{"learn":[4.463785664],"iteration":291,"passed_time":0.7732810713,"remaining_time":1.874941776},
{"learn":[4.460445831],"iteration":292,"passed_time":0.7741875947,"remaining_time":1.868090886},
{"learn":[4.45692492],"iteration":293,"passed_time":0.774980698,"remaining_time":1.861008071},
{"learn":[4.454031688],"iteration":294,"passed_time":0.7758124168,"remaining_time":1.854060183},
{"learn":[4.451672391],"iteration":295,"passed_time":0.7766562196,"remaining_time":1.84718236},
{"learn":[4.45031553],"iteration":296,"passed_time":0.7774925321,"remaining_time":1.840327441},
{"learn":[4.446782666],"iteration":297,"passed_time":0.7786806746,"remaining_time":1.834341723},
{"learn":[4.444369689],"iteration":298,"passed_time":0.7798322906,"remaining_time":1.82830246},
{"learn":[4.44411683],"iteration":299,"passed_time":0.7809328771,"remaining_time":1.822176713},
{"learn":[4.440876943],"iteration":300,"passed_time":0.7822675441,"remaining_time":1.816627951},
{"learn":[4.439336453],"iteration":301,"passed_time":0.7849930214,"remaining_time":1.814321619},
{"learn":[4.436666901],"iteration":302,"passed_time":0.7868189393,"remaining_time":1.809943237},
{"learn":[4.433043336],"iteration":303,"passed_time":0.7877424962,"remaining_time":1.803515715},
{"learn":[4.431419305],"iteration":304,"passed_time":0.7885478748,"remaining_time":1.796854993},
{"learn":[4.428859646],"iteration":305,"passed_time":0.7893756126,"remaining_time":1.790283252},
{"learn":[4.424552441],"iteration":306,"passed_time":0.7904804051,"remaining_time":1.784374335},
{"learn":[4.422706391],"iteration":307,"passed_time":0.7915185763,"remaining_time":1.778346931},
{"learn":[4.421427994],"iteration":308,"passed_time":0.7923948518,"remaining_time":1.771989782},
{"learn":[4.418733158],"iteration":309,"passed_time":0.7932435289,"remaining_time":1.765606564},
{"learn":[4.415656941],"iteration":310,"passed_time":0.794142776,"remaining_time":1.759370973},
{"learn":[4.410747417],"iteration":311,"passed_time":0.7983923081,"remaining_time":1.760557397},
{"learn":[4.408126521],"iteration":312,"passed_time":0.8005701323,"remaining_time":1.75716192},
{"learn":[4.407843853],"iteration":313,"passed_time":0.8017050911,"remaining_time":1.751495836},
{"learn":[4.405219398],"iteration":314,"passed_time":0.8025456417,"remaining_time":1.7452183},
{"learn":[4.402708465],"iteration":315,"passed_time":0.8033968915,"remaining_time":1.738998335},
{"learn":[4.40104971],"iteration":316,"passed_time":0.8042435393,"remaining_time":1.732802326},
{"learn":[4.400830038],"iteration":317,"passed_time":0.805291234,"remaining_time":1.727071137},
{"learn":[4.39784288],"iteration":318,"passed_time":0.8062244482,"remaining_time":1.721124919},
{"learn":[4.393741845],"iteration":319,"passed_time":0.8070526873,"remaining_time":1.714986961},
{"learn":[4.393425936],"iteration":320,"passed_time":0.8079317074,"remaining_time":1.708989499},
{"learn":[4.390505974],"iteration":321,"passed_time":0.8087175838,"remaining_time":1.702827707},
{"learn":[4.390305136],"iteration":322,"passed_time":0.8094301417,"remaining_time":1.696545529},
{"learn":[4.38568203],"iteration":323,"passed_time":0.814637383,"remaining_time":1.699675527},
{"learn":[4.383057135],"iteration":324,"passed_time":0.8166630252,"remaining_time":1.696146283},
{"learn":[4.380662684],"iteration":325,"passed_time":0.8176231997,"remaining_time":1.690423425},
{"learn":[4.37805727],"iteration":326,"passed_time":0.8185140165,"remaining_time":1.684586951},
{"learn":[4.373708319],"iteration":327,"passed_time":0.8197126988,"remaining_time":1.679411383},
{"learn":[4.36887921],"iteration":328,"passed_time":0.8205378894,"remaining_time":1.673498248},
{"learn":[4.367895929],"iteration":329,"passed_time":0.8213442336,"remaining_time":1.667577686},
{"learn":[4.362140573],"iteration":330,"passed_time":0.8221874984,"remaining_time":1.661762648},
{"learn":[4.361931924],"iteration":331,"passed_time":0.8229481174,"remaining_time":1.655811272},
{"learn":[4.359656377],"iteration":332,"passed_time":0.823740573,"remaining_time":1.649954841},
{"learn":[4.354281355],"iteration":333,"passed_time":0.8248679458,"remaining_time":1.644796563},
{"learn":[4.348589447],"iteration":334,"passed_time":0.8291279014,"remaining_time":1.645880759},
{"learn":[4.346355698],"iteration":335,"passed_time":0.8312312977,"remaining_time":1.642671374},
{"learn":[4.343894047],"iteration":336,"passed_time":0.8321968634,"remaining_time":1.637230031},
{"learn":[4.341561356],"iteration":337,"passed_time":0.8331163504,"remaining_time":1.631724923},
{"learn":[4.338869061],"iteration":338,"passed_time":0.834294572,"remaining_time":1.626751363},
{"learn":[4.333720063],"iteration":339,"passed_time":0.8352215997,"remaining_time":1.621312517},
{"learn":[4.330892223],"iteration":340,"passed_time":0.8360936447,"remaining_time":1.615793876},
{"learn":[4.328311474],"iteration":341,"passed_time":0.8369329086,"remaining_time":1.610239339},
{"learn":[4.324580133],"iteration":342,"passed_time":0.8377497156,"remaining_time":1.60466928},
{"learn":[4.323354432],"iteration":343,"passed_time":0.8385750949,"remaining_time":1.599143204},
{"learn":[4.323159553],"iteration":344,"passed_time":0.8393164551,"remaining_time":1.593484864},
{"learn":[4.318639682],"iteration":345,"passed_time":0.8432428924,"remaining_time":1.593875294},
{"learn":[4.312712208],"iteration":346,"passed_time":0.84457921,"remaining_time":1.58936664},
{"learn":[4.311461062],"iteration":347,"passed_time":0.8459720171,"remaining_time":1.584982055},
{"learn":[4.311178356],"iteration":348,"passed_time":0.846786344,"remaining_time":1.579535559},
{"learn":[4.311102505],"iteration":349,"passed_time":0.8480894771,"remaining_time":1.575023315},
{"learn":[4.310232308],"iteration":350,"passed_time":0.8491140406,"remaining_time":1.57001428},
{"learn":[4.305128197],"iteration":351,"passed_time":0.8501413902,"remaining_time":1.565033014},
{"learn":[4.304595496],"iteration":352,"passed_time":0.8509142097,"remaining_time":1.559607631},
{"learn":[4.3004992],"iteration":353,"passed_time":0.8517577028,"remaining_time":1.554337503},
{"learn":[4.297581524],"iteration":354,"passed_time":0.8525443187,"remaining_time":1.548988973},
{"learn":[4.297355825],"iteration":355,"passed_time":0.8533308374,"remaining_time":1.543665897},
{"learn":[4.295758715],"iteration":356,"passed_time":0.854138705,"remaining_time":1.538406687},
{"learn":[4.292500657],"iteration":357,"passed_time":0.8588173672,"remaining_time":1.540113826},
{"learn":[4.290797586],"iteration":358,"passed_time":0.8602276319,"remaining_time":1.535949616},
{"learn":[4.286410608],"iteration":359,"passed_time":0.8611735704,"remaining_time":1.530975236},
{"learn":[4.280278245],"iteration":360,"passed_time":0.8622643058,"remaining_time":1.526279478},
{"learn":[4.279941283],"iteration":361,"passed_time":0.8630510468,"remaining_time":1.521067867},
{"learn":[4.274426275],"iteration":362,"passed_time":0.863868009,"remaining_time":1.515933669},
{"learn":[4.273567658],"iteration":363,"passed_time":0.8646897457,"remaining_time":1.510831534},
{"learn":[4.269488271],"iteration":364,"passed_time":0.86548151,"remaining_time":1.505700709},
{"learn":[4.266838205],"iteration":365,"passed_time":0.8663357874,"remaining_time":1.500701883},
{"learn":[4.263456509],"iteration":366,"passed_time":0.8671501987,"remaining_time":1.495656882},
{"learn":[4.260360204],"iteration":367,"passed_time":0.8679592196,"remaining_time":1.490625616},
{"learn":[4.255120549],"iteration":368,"passed_time":0.8687727534,"remaining_time":1.485624952},
{"learn":[4.252582211],"iteration":369,"passed_time":0.8726403771,"remaining_time":1.485847128},
{"learn":[4.247857931],"iteration":370,"passed_time":0.8741217956,"remaining_time":1.482001643},
{"learn":[4.245288911],"iteration":371,"passed_time":0.8752914387,"remaining_time":1.477642536},
{"learn":[4.24048515],"iteration":372,"passed_time":0.8763956376,"remaining_time":1.473190522},
{"learn":[4.2378365],"iteration":373,"passed_time":0.8772427013,"remaining_time":1.468326019},
{"learn":[4.236751063],"iteration":374,"passed_time":0.8780468143,"remaining_time":1.463411357},
{"learn":[4.233240093],"iteration":375,"passed_time":0.8788768659,"remaining_time":1.458561607},
{"learn":[4.230358421],"iteration":376,"passed_time":0.8796687024,"remaining_time":1.453670031},
{"learn":[4.225853583],"iteration":377,"passed_time":0.880512535,"remaining_time":1.448885706},
{"learn":[4.224702126],"iteration":378,"passed_time":0.8812821414,"remaining_time":1.444000554},
{"learn":[4.224361982],"iteration":379,"passed_time":0.8820280641,"remaining_time":1.43909842},
{"learn":[4.223787954],"iteration":380,"passed_time":0.8827909859,"remaining_time":1.434245723},
{"learn":[4.22144054],"iteration":381,"passed_time":0.883612921,"remaining_time":1.429509909},
{"learn":[4.217739335],"iteration":382,"passed_time":0.8875717711,"remaining_time":1.429847997},
{"learn":[4.215611665],"iteration":383,"passed_time":0.8892392852,"remaining_time":1.42648802},
{"learn":[4.210236863],"iteration":384,"passed_time":0.8905391599,"remaining_time":1.422549567},
{"learn":[4.208454294],"iteration":385,"passed_time":0.8918181277,"remaining_time":1.41859153},
{"learn":[4.207446501],"iteration":386,"passed_time":0.8927357316,"remaining_time":1.414074944},
{"learn":[4.204985442],"iteration":387,"passed_time":0.8938231805,"remaining_time":1.40984481},
{"learn":[4.202796622],"iteration":388,"passed_time":0.8947689708,"remaining_time":1.405408332},
{"learn":[4.199774004],"iteration":389,"passed_time":0.8957367737,"remaining_time":1.401024185},
{"learn":[4.199458358],"iteration":390,"passed_time":0.8965824472,"remaining_time":1.39646729},
{"learn":[4.19751254],"iteration":391,"passed_time":0.8975903724,"remaining_time":1.392180986},
{"learn":[4.195201346],"iteration":392,"passed_time":0.8989017264,"remaining_time":1.38838002},
{"learn":[4.190593508],"iteration":393,"passed_time":0.9019655763,"remaining_time":1.387287155},
{"learn":[4.187212054],"iteration":394,"passed_time":0.9041869488,"remaining_time":1.384893934},
{"learn":[4.184984466],"iteration":395,"passed_time":0.9054176491,"remaining_time":1.380990556},
{"learn":[4.182832144],"iteration":396,"passed_time":0.9070885591,"remaining_time":1.377769272},
{"learn":[4.179752812],"iteration":397,"passed_time":0.9087070609,"remaining_time":1.374476509},
{"learn":[4.17878934],"iteration":398,"passed_time":0.910172497,"remaining_time":1.370961581},
{"learn":[4.174548229],"iteration":399,"passed_time":0.9167858703,"remaining_time":1.375178805},
{"learn":[4.168872556],"iteration":400,"passed_time":0.9183976496,"remaining_time":1.371870803},
{"learn":[4.163926494],"iteration":401,"passed_time":0.9206501935,"remaining_time":1.369524417},
{"learn":[4.159485076],"iteration":402,"passed_time":0.9220641907,"remaining_time":1.365936282},
{"learn":[4.155926102],"iteration":403,"passed_time":0.923263074,"remaining_time":1.362041565},
{"learn":[4.153540115],"iteration":404,"passed_time":0.9245125947,"remaining_time":1.358234553},
{"learn":[4.150983044],"iteration":405,"passed_time":0.9257195673,"remaining_time":1.354377889},
{"learn":[4.146539132],"iteration":406,"passed_time":0.9268987364,"remaining_time":1.350493736},
{"learn":[4.144869174],"iteration":407,"passed_time":0.9331530735,"remaining_time":1.353986813},
{"learn":[4.142825962],"iteration":408,"passed_time":0.9344905001,"remaining_time":1.350327348},
{"learn":[4.142467378],"iteration":409,"passed_time":0.9354323636,"remaining_time":1.346109987},
{"learn":[4.141800768],"iteration":410,"passed_time":0.9366103363,"remaining_time":1.34224693},
{"learn":[4.140107084],"iteration":411,"passed_time":0.9376235561,"remaining_time":1.338161774},
{"learn":[4.136243196],"iteration":412,"passed_time":0.9386830526,"remaining_time":1.334157269},
{"learn":[4.133618439],"iteration":413,"passed_time":0.9397131939,"remaining_time":1.330125439},
{"learn":[4.131053025],"iteration":414,"passed_time":0.9407835518,"remaining_time":1.326164766},
{"learn":[4.128379975],"iteration":415,"passed_time":0.9423343104,"remaining_time":1.322892397},
{"learn":[4.127068571],"iteration":416,"passed_time":0.9470488565,"remaining_time":1.324051519},
{"learn":[4.125969877],"iteration":417,"passed_time":0.9489180858,"remaining_time":1.321220875},
{"learn":[4.123893633],"iteration":418,"passed_time":0.9500299154,"remaining_time":1.317344584},
{"learn":[4.119643722],"iteration":419,"passed_time":0.9513789978,"remaining_time":1.313809092},
{"learn":[4.11465686],"iteration":420,"passed_time":0.9524270014,"remaining_time":1.309869914},
{"learn":[4.111565986],"iteration":421,"passed_time":0.9535421638,"remaining_time":1.306036423},
{"learn":[4.106322452],"iteration":422,"passed_time":0.9545413929,"remaining_time":1.302057645},
{"learn":[4.104222175],"iteration":423,"passed_time":0.9554886893,"remaining_time":1.29802237},
{"learn":[4.103008002],"iteration":424,"passed_time":0.956414483,"remaining_time":1.293972536},
{"learn":[4.099176337],"iteration":425,"passed_time":0.9582326461,"remaining_time":1.291139763},
{"learn":[4.096525716],"iteration":426,"passed_time":0.9630259119,"remaining_time":1.292304093},
{"learn":[4.094967724],"iteration":427,"passed_time":0.964450651,"remaining_time":1.28893872},
{"learn":[4.094683584],"iteration":428,"passed_time":0.9657721806,"remaining_time":1.285445024},
{"learn":[4.091096563],"iteration":429,"passed_time":0.9690047224,"remaining_time":1.284494632},
{"learn":[4.089178677],"iteration":430,"passed_time":0.9705348425,"remaining_time":1.281286138},
{"learn":[4.085335077],"iteration":431,"passed_time":0.9717118725,"remaining_time":1.277621166},
{"learn":[4.084852122],"iteration":432,"passed_time":0.975665801,"remaining_time":1.277603947},
{"learn":[4.080322952],"iteration":433,"passed_time":0.9779097809,"remaining_time":1.275338562},
{"learn":[4.077449519],"iteration":434,"passed_time":0.9792423865,"remaining_time":1.271889536},
{"learn":[4.076568374],"iteration":435,"passed_time":0.9802602495,"remaining_time":1.268043075},
{"learn":[4.076071793],"iteration":436,"passed_time":0.9812069166,"remaining_time":1.264117835},
{"learn":[4.075027644],"iteration":437,"passed_time":0.9822081701,"remaining_time":1.260276236},
{"learn":[4.07020837],"iteration":438,"passed_time":0.9831390855,"remaining_time":1.256357692},
{"learn":[4.06833694],"iteration":439,"passed_time":0.9840439241,"remaining_time":1.25241954},
{"learn":[4.063936568],"iteration":440,"passed_time":0.9897282445,"remaining_time":1.254553489},
{"learn":[4.061734926],"iteration":441,"passed_time":0.9912865529,"remaining_time":1.251443205},
{"learn":[4.060815619],"iteration":442,"passed_time":0.9924554372,"remaining_time":1.24785029},
{"learn":[4.056407489],"iteration":443,"passed_time":0.9935811145,"remaining_time":1.244214188},
{"learn":[4.05238936],"iteration":444,"passed_time":0.9946999546,"remaining_time":1.240580842},
{"learn":[4.049685254],"iteration":445,"passed_time":0.995656801,"remaining_time":1.236757551},
{"learn":[4.045162016],"iteration":446,"passed_time":0.9968030198,"remaining_time":1.233181365},
{"learn":[4.042955482],"iteration":447,"passed_time":0.998411124,"remaining_time":1.230185135},
{"learn":[4.041467663],"iteration":448,"passed_time":0.9996792312,"remaining_time":1.226777854},
{"learn":[4.038920476],"iteration":449,"passed_time":1.004309008,"remaining_time":1.227488788},
{"learn":[4.036694383],"iteration":450,"passed_time":1.006431201,"remaining_time":1.225123569},
{"learn":[4.034999007],"iteration":451,"passed_time":1.008466398,"remaining_time":1.222653952},
{"learn":[4.031928018],"iteration":452,"passed_time":1.009523798,"remaining_time":1.219005557},
{"learn":[4.028718143],"iteration":453,"passed_time":1.010432816,"remaining_time":1.215190127},
{"learn":[4.027401978],"iteration":454,"passed_time":1.011253798,"remaining_time":1.211282021},
{"learn":[4.025930598],"iteration":455,"passed_time":1.012220697,"remaining_time":1.207561533},
{"learn":[4.021074523],"iteration":456,"passed_time":1.013231836,"remaining_time":1.20390566},
{"learn":[4.020268486],"iteration":457,"passed_time":1.014270697,"remaining_time":1.200294144},
{"learn":[4.017986361],"iteration":458,"passed_time":1.018993474,"remaining_time":1.201035881},
{"learn":[4.014814804],"iteration":459,"passed_time":1.020767966,"remaining_time":1.198292829},
{"learn":[4.009704796],"iteration":460,"passed_time":1.022056332,"remaining_time":1.194985602},
{"learn":[4.008440457],"iteration":461,"passed_time":1.023035858,"remaining_time":1.191327471},
{"learn":[4.004854849],"iteration":462,"passed_time":1.024017369,"remaining_time":1.187683212},
{"learn":[4.000898028],"iteration":463,"passed_time":1.024971391,"remaining_time":1.184018676},
{"learn":[3.996617985],"iteration":464,"passed_time":1.026229316,"remaining_time":1.18071545},
{"learn":[3.995443319],"iteration":465,"passed_time":1.027193216,"remaining_time":1.177084072},
{"learn":[3.990771995],"iteration":466,"passed_time":1.028217899,"remaining_time":1.173533491},
{"learn":[3.989249359],"iteration":467,"passed_time":1.029152268,"remaining_time":1.16989104},
{"learn":[3.986599538],"iteration":468,"passed_time":1.033714503,"remaining_time":1.170367593},
{"learn":[3.985628919],"iteration":469,"passed_time":1.035342481,"remaining_time":1.167513862},
{"learn":[3.985086112],"iteration":470,"passed_time":1.036727729,"remaining_time":1.164392715},
{"learn":[3.98466839],"iteration":471,"passed_time":1.037672485,"remaining_time":1.16078617},
{"learn":[3.984233894],"iteration":472,"passed_time":1.038647691,"remaining_time":1.157224806},
{"learn":[3.981855845],"iteration":473,"passed_time":1.039847965,"remaining_time":1.153924113},
{"learn":[3.978684264],"iteration":474,"passed_time":1.04082783,"remaining_time":1.150388654},
{"learn":[3.974361269],"iteration":475,"passed_time":1.04185584,"remaining_time":1.146916933},
{"learn":[3.972074049],"iteration":476,"passed_time":1.042793227,"remaining_time":1.143356096},
{"learn":[3.97191982],"iteration":477,"passed_time":1.043708225,"remaining_time":1.139781785},
{"learn":[3.969616848],"iteration":478,"passed_time":1.044673473,"remaining_time":1.136273235},
{"learn":[3.968533527],"iteration":479,"passed_time":1.049628038,"remaining_time":1.137097042},
{"learn":[3.967568753],"iteration":480,"passed_time":1.051136655,"remaining_time":1.134178636},
{"learn":[3.966232553],"iteration":481,"passed_time":1.052147321,"remaining_time":1.130730938},
{"learn":[3.961522393],"iteration":482,"passed_time":1.053189833,"remaining_time":1.127327419},
{"learn":[3.955829553],"iteration":483,"passed_time":1.054489145,"remaining_time":1.124207435},
{"learn":[3.954248095],"iteration":484,"passed_time":1.05553645,"remaining_time":1.120827364},
{"learn":[3.951922606],"iteration":485,"passed_time":1.056504331,"remaining_time":1.117372894},
{"learn":[3.94978202],"iteration":486,"passed_time":1.057446831,"remaining_time":1.113901897},
{"learn":[3.949518999],"iteration":487,"passed_time":1.058396526,"remaining_time":1.110448815},
{"learn":[3.945431216],"iteration":488,"passed_time":1.059360849,"remaining_time":1.107021255},
{"learn":[3.943249086],"iteration":489,"passed_time":1.063726083,"remaining_time":1.107143474},
{"learn":[3.941981548],"iteration":490,"passed_time":1.065496522,"remaining_time":1.104557494},
{"learn":[3.936600517],"iteration":491,"passed_time":1.066853528,"remaining_time":1.101547952},
{"learn":[3.934476885],"iteration":492,"passed_time":1.067821173,"remaining_time":1.098144695},
{"learn":[3.93045798],"iteration":493,"passed_time":1.068890543,"remaining_time":1.094855495},
{"learn":[3.925977375],"iteration":494,"passed_time":1.070011404,"remaining_time":1.091627796},
{"learn":[3.92457993],"iteration":495,"passed_time":1.071030656,"remaining_time":1.088305344},
{"learn":[3.919849146],"iteration":496,"passed_time":1.072012996,"remaining_time":1.084954803},
{"learn":[3.919681964],"iteration":497,"passed_time":1.07289617,"remaining_time":1.08151381},
{"learn":[3.917633027],"iteration":498,"passed_time":1.073952368,"remaining_time":1.078256786},
{"learn":[3.916616419],"iteration":499,"passed_time":1.074917786,"remaining_time":1.074917786},
{"learn":[3.912896166],"iteration":500,"passed_time":1.079903793,"remaining_time":1.0755928},
{"learn":[3.912769674],"iteration":501,"passed_time":1.081472511,"remaining_time":1.0728552},
{"learn":[3.909373788],"iteration":502,"passed_time":1.082949312,"remaining_time":1.070031427},
{"learn":[3.906706036],"iteration":503,"passed_time":1.084852781,"remaining_time":1.067632895},
{"learn":[3.903895664],"iteration":504,"passed_time":1.086145205,"remaining_time":1.064637379},
{"learn":[3.902982967],"iteration":505,"passed_time":1.08709265,"remaining_time":1.061311797},
{"learn":[3.900905528],"iteration":506,"passed_time":1.088032849,"remaining_time":1.05798855},
{"learn":[3.897463465],"iteration":507,"passed_time":1.089041292,"remaining_time":1.054740779},
{"learn":[3.895918033],"iteration":508,"passed_time":1.089956716,"remaining_time":1.051412078},
{"learn":[3.893921936],"iteration":509,"passed_time":1.093195521,"remaining_time":1.050325109},
{"learn":[3.890237934],"iteration":510,"passed_time":1.095517705,"remaining_time":1.048352559},
{"learn":[3.887311613],"iteration":511,"passed_time":1.096977469,"remaining_time":1.04555665},
{"learn":[3.884869735],"iteration":512,"passed_time":1.098103107,"remaining_time":1.042448758},
{"learn":[3.882101231],"iteration":513,"passed_time":1.099074807,"remaining_time":1.039203028},
{"learn":[3.88060368],"iteration":514,"passed_time":1.1000077,"remaining_time":1.035929581},
{"learn":[3.877726076],"iteration":515,"passed_time":1.100881809,"remaining_time":1.032610069},
{"learn":[3.874938145],"iteration":516,"passed_time":1.101865799,"remaining_time":1.029402671},
{"learn":[3.874340833],"iteration":517,"passed_time":1.102850699,"remaining_time":1.026204704},
{"learn":[3.873105224],"iteration":518,"passed_time":1.10385278,"remaining_time":1.023031189},
{"learn":[3.869800236],"iteration":519,"passed_time":1.104762152,"remaining_time":1.019780448},
{"learn":[3.867932518],"iteration":520,"passed_time":1.109190891,"remaining_time":1.019774351},
{"learn":[3.866666962],"iteration":521,"passed_time":1.111397676,"remaining_time":1.017716646},
{"learn":[3.865527652],"iteration":522,"passed_time":1.112538888,"remaining_time":1.014686519},
{"learn":[3.861900081],"iteration":523,"passed_time":1.113508639,"remaining_time":1.011507847},
{"learn":[3.858502887],"iteration":524,"passed_time":1.114599527,"remaining_time":1.008447191},
{"learn":[3.858335097],"iteration":525,"passed_time":1.115498556,"remaining_time":1.005221132},
{"learn":[3.855719306],"iteration":526,"passed_time":1.116411075,"remaining_time":1.002016012},
{"learn":[3.855137428],"iteration":527,"passed_time":1.117414633,"remaining_time":0.9989009602},
{"learn":[3.851985706],"iteration":528,"passed_time":1.118334261,"remaining_time":0.9957191624},
{"learn":[3.851051809],"iteration":529,"passed_time":1.119230563,"remaining_time":0.9925252166},
{"learn":[3.850679146],"iteration":530,"passed_time":1.12017032,"remaining_time":0.9893783054},
{"learn":[3.848179484],"iteration":531,"passed_time":1.124399928,"remaining_time":0.9891337716},
{"learn":[3.844551071],"iteration":532,"passed_time":1.12629502,"remaining_time":0.9868288452},
{"learn":[3.841604794],"iteration":533,"passed_time":1.127535456,"remaining_time":0.9839541617},
{"learn":[3.83969656],"iteration":534,"passed_time":1.128515585,"remaining_time":0.98085934},
{"learn":[3.836811463],"iteration":535,"passed_time":1.129499837,"remaining_time":0.9777759782},
{"learn":[3.834182551],"iteration":536,"passed_time":1.130494409,"remaining_time":0.9747093325},
{"learn":[3.828012842],"iteration":537,"passed_time":1.131430843,"remaining_time":0.9716004637},
{"learn":[3.826636176],"iteration":538,"passed_time":1.132348434,"remaining_time":0.9684835396},
{"learn":[3.826189798],"iteration":539,"passed_time":1.133237524,"remaining_time":0.9653504832},
{"learn":[3.824104738],"iteration":540,"passed_time":1.134134815,"remaining_time":0.9622326807},
{"learn":[3.82300218],"iteration":541,"passed_time":1.134969911,"remaining_time":0.9590705151},
{"learn":[3.817146402],"iteration":542,"passed_time":1.138636158,"remaining_time":0.9582996761},
{"learn":[3.814638044],"iteration":543,"passed_time":1.140359737,"remaining_time":0.95588978},
{"learn":[3.812979573],"iteration":544,"passed_time":1.141463448,"remaining_time":0.9529648972},
{"learn":[3.811938825],"iteration":545,"passed_time":1.142527536,"remaining_time":0.9500137387},
{"learn":[3.811479418],"iteration":546,"passed_time":1.143838983,"remaining_time":0.9472743311},
{"learn":[3.80742981],"iteration":547,"passed_time":1.144872915,"remaining_time":0.9443112365},
{"learn":[3.805097043],"iteration":548,"passed_time":1.145796766,"remaining_time":0.9412647384},
{"learn":[3.801577232],"iteration":549,"passed_time":1.146781697,"remaining_time":0.9382759342},
{"learn":[3.799762083],"iteration":550,"passed_time":1.147679153,"remaining_time":0.935223121},
{"learn":[3.796393455],"iteration":551,"passed_time":1.148567897,"remaining_time":0.9321710466},
{"learn":[3.793486459],"iteration":552,"passed_time":1.149516462,"remaining_time":0.9291751514},
{"learn":[3.792006091],"iteration":553,"passed_time":1.153913178,"remaining_time":0.9289625948},
{"learn":[3.78932128],"iteration":554,"passed_time":1.155530199,"remaining_time":0.9265061959},
{"learn":[3.787581812],"iteration":555,"passed_time":1.156741848,"remaining_time":0.9237291013},
{"learn":[3.785308865],"iteration":556,"passed_time":1.157693265,"remaining_time":0.9207506579},
{"learn":[3.78465475],"iteration":557,"passed_time":1.158639017,"remaining_time":0.9177749918},
{"learn":[3.780498869],"iteration":558,"passed_time":1.159610879,"remaining_time":0.9148271871},
{"learn":[3.778734909],"iteration":559,"passed_time":1.160553432,"remaining_time":0.911863411},
{"learn":[3.778652349],"iteration":560,"passed_time":1.16146154,"remaining_time":0.9088798862},
{"learn":[3.777928006],"iteration":561,"passed_time":1.162361591,"remaining_time":0.9058974677},
{"learn":[3.776131406],"iteration":562,"passed_time":1.16322392,"remaining_time":0.9028931668},
{"learn":[3.772925617],"iteration":563,"passed_time":1.164196837,"remaining_time":0.8999819523},
{"learn":[3.7727745],"iteration":564,"passed_time":1.165088087,"remaining_time":0.8970147218},
{"learn":[3.771763073],"iteration":565,"passed_time":1.169641268,"remaining_time":0.8968627388},
{"learn":[3.768738162],"iteration":566,"passed_time":1.170643799,"remaining_time":0.8939837128},
{"learn":[3.767220794],"iteration":567,"passed_time":1.171595759,"remaining_time":0.891072831},
{"learn":[3.766691102],"iteration":568,"passed_time":1.172555778,"remaining_time":0.8881749392},
{"learn":[3.766259335],"iteration":569,"passed_time":1.173474866,"remaining_time":0.8852529688},
{"learn":[3.76116362],"iteration":570,"passed_time":1.174429359,"remaining_time":0.8823646145},
{"learn":[3.758633056],"iteration":571,"passed_time":1.175387167,"remaining_time":0.8794855023},
{"learn":[3.754603809],"iteration":572,"passed_time":1.176313405,"remaining_time":0.8765895705},
{"learn":[3.754070549],"iteration":573,"passed_time":1.177206723,"remaining_time":0.8736760696},
{"learn":[3.750534319],"iteration":574,"passed_time":1.178101168,"remaining_time":0.8707704282},
{"learn":[3.746491516],"iteration":575,"passed_time":1.17905738,"remaining_time":0.8679172382},
{"learn":[3.744210544],"iteration":576,"passed_time":1.18016471,"remaining_time":0.8651814078},
{"learn":[3.742929991],"iteration":577,"passed_time":1.182267978,"remaining_time":0.8631783509},
{"learn":[3.740402992],"iteration":578,"passed_time":1.183327547,"remaining_time":0.8604160578},
{"learn":[3.739644243],"iteration":579,"passed_time":1.184264759,"remaining_time":0.8575710323},
{"learn":[3.737529404],"iteration":580,"passed_time":1.185206151,"remaining_time":0.854735589},
{"learn":[3.737196923],"iteration":581,"passed_time":1.186171572,"remaining_time":0.8519239129},
{"learn":[3.733954464],"iteration":582,"passed_time":1.187115682,"remaining_time":0.8491033266},
{"learn":[3.731608623],"iteration":583,"passed_time":1.188054088,"remaining_time":0.8462851037},
{"learn":[3.729843952],"iteration":584,"passed_time":1.188990178,"remaining_time":0.8434716647},
{"learn":[3.727223798],"iteration":585,"passed_time":1.189964245,"remaining_time":0.840691463},
{"learn":[3.725351667],"iteration":586,"passed_time":1.19096404,"remaining_time":0.8379355169},
{"learn":[3.725026912],"iteration":587,"passed_time":1.191949932,"remaining_time":0.8351758025},
{"learn":[3.721974565],"iteration":588,"passed_time":1.192892501,"remaining_time":0.8323918809},
{"learn":[3.720269493],"iteration":589,"passed_time":1.193791093,"remaining_time":0.8295836407},
{"learn":[3.718907466],"iteration":590,"passed_time":1.195237796,"remaining_time":0.8271611818},
{"learn":[3.715602912],"iteration":591,"passed_time":1.19636662,"remaining_time":0.8245229411},
{"learn":[3.714463059],"iteration":592,"passed_time":1.197395553,"remaining_time":0.821821231},
{"learn":[3.710802077],"iteration":593,"passed_time":1.198435107,"remaining_time":0.8191324134},
{"learn":[3.708032435],"iteration":594,"passed_time":1.199482727,"remaining_time":0.8164546291},
{"learn":[3.703788939],"iteration":595,"passed_time":1.200394101,"remaining_time":0.813689961},
{"learn":[3.702500944],"iteration":596,"passed_time":1.201352455,"remaining_time":0.8109632152},
{"learn":[3.698196925],"iteration":597,"passed_time":1.202288898,"remaining_time":0.8082276541},
{"learn":[3.69658891],"iteration":598,"passed_time":1.203232468,"remaining_time":0.8055028712},
{"learn":[3.696124066],"iteration":599,"passed_time":1.204165564,"remaining_time":0.8027770424},
{"learn":[3.693537052],"iteration":600,"passed_time":1.205151736,"remaining_time":0.8000924169},
{"learn":[3.691343275],"iteration":601,"passed_time":1.20621968,"remaining_time":0.7974674958},
{"learn":[3.690973831],"iteration":602,"passed_time":1.207186254,"remaining_time":0.7947809995},
{"learn":[3.686151073],"iteration":603,"passed_time":1.208102903,"remaining_time":0.7920674664},
{"learn":[3.683921982],"iteration":604,"passed_time":1.20956566,"remaining_time":0.7897164225},
{"learn":[3.679975271],"iteration":605,"passed_time":1.210725471,"remaining_time":0.7871713457},
{"learn":[3.674047638],"iteration":606,"passed_time":1.211716934,"remaining_time":0.784521837},
{"learn":[3.673151794],"iteration":607,"passed_time":1.212697176,"remaining_time":0.7818705478},
{"learn":[3.670953108],"iteration":608,"passed_time":1.213643527,"remaining_time":0.7792029872},
{"learn":[3.6703947],"iteration":609,"passed_time":1.214593403,"remaining_time":0.776543323},
{"learn":[3.668433805],"iteration":610,"passed_time":1.215500119,"remaining_time":0.7738617781},
{"learn":[3.668304956],"iteration":611,"passed_time":1.216379602,"remaining_time":0.7711687673},
{"learn":[3.667880012],"iteration":612,"passed_time":1.217336083,"remaining_time":0.7685302843},
{"learn":[3.667282264],"iteration":613,"passed_time":1.218274164,"remaining_time":0.7658857124},
{"learn":[3.664611483],"iteration":614,"passed_time":1.219287756,"remaining_time":0.7632939614},
{"learn":[3.662543394],"iteration":615,"passed_time":1.220285442,"remaining_time":0.7606974183},
{"learn":[3.659041959],"iteration":616,"passed_time":1.221252256,"remaining_time":0.7580868947},
{"learn":[3.656868545],"iteration":617,"passed_time":1.222336095,"remaining_time":0.7555540264},
{"learn":[3.654785614],"iteration":618,"passed_time":1.223377269,"remaining_time":0.752999579},
{"learn":[3.654566096],"iteration":619,"passed_time":1.224351338,"remaining_time":0.7504088845},
{"learn":[3.651007045],"iteration":620,"passed_time":1.225409525,"remaining_time":0.7478747342},
{"learn":[3.648921786],"iteration":621,"passed_time":1.22644012,"remaining_time":0.7453285619},
{"learn":[3.647655706],"iteration":622,"passed_time":1.227404501,"remaining_time":0.7427471861},
{"learn":[3.647241144],"iteration":623,"passed_time":1.22828455,"remaining_time":0.7401201774},
{"learn":[3.644195689],"iteration":624,"passed_time":1.229232376,"remaining_time":0.7375394258},
{"learn":[3.642632246],"iteration":625,"passed_time":1.230153908,"remaining_time":0.7349481817},
{"learn":[3.642523322],"iteration":626,"passed_time":1.230882494,"remaining_time":0.7322474804},
{"learn":[3.641494659],"iteration":627,"passed_time":1.23182525,"remaining_time":0.7296799251},
{"learn":[3.63976496],"iteration":628,"passed_time":1.23277202,"remaining_time":0.7271199036},
{"learn":[3.637945652],"iteration":629,"passed_time":1.233762476,"remaining_time":0.7245906603},
{"learn":[3.636233667],"iteration":630,"passed_time":1.234713258,"remaining_time":0.722043094},
{"learn":[3.635304404],"iteration":631,"passed_time":1.235667522,"remaining_time":0.7195026076},
{"learn":[3.632234951],"iteration":632,"passed_time":1.236638084,"remaining_time":0.7169765826},
{"learn":[3.631630987],"iteration":633,"passed_time":1.237591989,"remaining_time":0.7144458483},
{"learn":[3.630301009],"iteration":634,"passed_time":1.238530973,"remaining_time":0.7119115044},
{"learn":[3.629077964],"iteration":635,"passed_time":1.239494713,"remaining_time":0.7093963452},
{"learn":[3.628004522],"iteration":636,"passed_time":1.240429968,"remaining_time":0.7068698247},
{"learn":[3.625062876],"iteration":637,"passed_time":1.241385177,"remaining_time":0.7043596143},
{"learn":[3.624917986],"iteration":638,"passed_time":1.242311613,"remaining_time":0.7018380163},
{"learn":[3.622887087],"iteration":639,"passed_time":1.243269421,"remaining_time":0.6993390495},
{"learn":[3.621220865],"iteration":640,"passed_time":1.244206999,"remaining_time":0.6968335612},
{"learn":[3.621143844],"iteration":641,"passed_time":1.245099951,"remaining_time":0.6943080726},
{"learn":[3.620822821],"iteration":642,"passed_time":1.246062206,"remaining_time":0.6918261395},
{"learn":[3.619202826],"iteration":643,"passed_time":1.247004171,"remaining_time":0.6893377092},
{"learn":[3.618204882],"iteration":644,"passed_time":1.247907213,"remaining_time":0.6868326522},
{"learn":[3.614259666],"iteration":645,"passed_time":1.249386487,"remaining_time":0.6846483229},
{"learn":[3.613415661],"iteration":646,"passed_time":1.250568979,"remaining_time":0.6823042498},
{"learn":[3.611096773],"iteration":647,"passed_time":1.251563911,"remaining_time":0.6798618775},
{"learn":[3.610820695],"iteration":648,"passed_time":1.252472294,"remaining_time":0.6773771572},
{"learn":[3.609290065],"iteration":649,"passed_time":1.25339175,"remaining_time":0.67490325},
{"learn":[3.60897947],"iteration":650,"passed_time":1.25429698,"remaining_time":0.6724264916},
{"learn":[3.606570702],"iteration":651,"passed_time":1.255253346,"remaining_time":0.6699818475},
{"learn":[3.606292637],"iteration":652,"passed_time":1.256201552,"remaining_time":0.6675374252},
{"learn":[3.602753838],"iteration":653,"passed_time":1.25712631,"remaining_time":0.6650851732},
{"learn":[3.599755869],"iteration":654,"passed_time":1.258036739,"remaining_time":0.6626300379},
{"learn":[3.599509575],"iteration":655,"passed_time":1.258978925,"remaining_time":0.6601962658},
{"learn":[3.595337722],"iteration":656,"passed_time":1.259882041,"remaining_time":0.6577466366},
{"learn":[3.595168561],"iteration":657,"passed_time":1.260844913,"remaining_time":0.6553327664},
{"learn":[3.59290559],"iteration":658,"passed_time":1.261750315,"remaining_time":0.6528935621},
{"learn":[3.592015928],"iteration":659,"passed_time":1.262613125,"remaining_time":0.6504370645},
{"learn":[3.590680403],"iteration":660,"passed_time":1.263968455,"remaining_time":0.6482379824},
{"learn":[3.590361532],"iteration":661,"passed_time":1.264977576,"remaining_time":0.6458646839},
{"learn":[3.589069739],"iteration":662,"passed_time":1.265910084,"remaining_time":0.6434565584},
{"learn":[3.585010186],"iteration":663,"passed_time":1.26688648,"remaining_time":0.6410750862},
{"learn":[3.582997552],"iteration":664,"passed_time":1.26781629,"remaining_time":0.6386743717},
{"learn":[3.582119256],"iteration":665,"passed_time":1.268777961,"remaining_time":0.6362940525},
{"learn":[3.579019356],"iteration":666,"passed_time":1.269794573,"remaining_time":0.6339454163},
{"learn":[3.57719559],"iteration":667,"passed_time":1.270756825,"remaining_time":0.6315737516},
{"learn":[3.574050046],"iteration":668,"passed_time":1.271674509,"remaining_time":0.629184249},
{"learn":[3.572204518],"iteration":669,"passed_time":1.272666163,"remaining_time":0.626835573},
{"learn":[3.569508025],"iteration":670,"passed_time":1.273583365,"remaining_time":0.6244544368},
{"learn":[3.566268704],"iteration":671,"passed_time":1.274528363,"remaining_time":0.622091225},
{"learn":[3.562564052],"iteration":672,"passed_time":1.275551235,"remaining_time":0.6197700653},
{"learn":[3.561173586],"iteration":673,"passed_time":1.276545039,"remaining_time":0.6174386983},
{"learn":[3.559551904],"iteration":674,"passed_time":1.277584675,"remaining_time":0.6151333621},
{"learn":[3.558593054],"iteration":675,"passed_time":1.278539638,"remaining_time":0.6127911874},
{"learn":[3.555647008],"iteration":676,"passed_time":1.279497032,"remaining_time":0.6104542709},
{"learn":[3.553100059],"iteration":677,"passed_time":1.280462522,"remaining_time":0.6081252684},
{"learn":[3.55085578],"iteration":678,"passed_time":1.281404064,"remaining_time":0.6057889612},
{"learn":[3.550737965],"iteration":679,"passed_time":1.282235384,"remaining_time":0.6034048867},
{"learn":[3.549408772],"iteration":680,"passed_time":1.283184567,"remaining_time":0.6010805827},
{"learn":[3.547390589],"iteration":681,"passed_time":1.284124997,"remaining_time":0.59875623},
{"learn":[3.54723575],"iteration":682,"passed_time":1.285065076,"remaining_time":0.5964357673},
{"learn":[3.543988891],"iteration":683,"passed_time":1.285892767,"remaining_time":0.5940674184},
{"learn":[3.543868508],"iteration":684,"passed_time":1.286645239,"remaining_time":0.5916689786},
{"learn":[3.542752124],"iteration":685,"passed_time":1.287430905,"remaining_time":0.5892905307},
{"learn":[3.541334315],"iteration":686,"passed_time":1.288247478,"remaining_time":0.5869308013},
{"learn":[3.540208266],"iteration":687,"passed_time":1.289016364,"remaining_time":0.5845539325},
{"learn":[3.537730983],"iteration":688,"passed_time":1.28985916,"remaining_time":0.5822150923},
{"learn":[3.53419867],"iteration":689,"passed_time":1.290787722,"remaining_time":0.5799191215},
{"learn":[3.532628335],"iteration":690,"passed_time":1.2916614,"remaining_time":0.5776025654},
{"learn":[3.532204987],"iteration":691,"passed_time":1.292478758,"remaining_time":0.5752651121},
{"learn":[3.530618147],"iteration":692,"passed_time":1.293278826,"remaining_time":0.572924386},
{"learn":[3.528909306],"iteration":693,"passed_time":1.294073387,"remaining_time":0.5705856719},
{"learn":[3.526700678],"iteration":694,"passed_time":1.294871889,"remaining_time":0.5682531309},
{"learn":[3.526439574],"iteration":695,"passed_time":1.295651384,"remaining_time":0.5659166965},
{"learn":[3.525784216],"iteration":696,"passed_time":1.296456252,"remaining_time":0.5635957595},
{"learn":[3.524112693],"iteration":697,"passed_time":1.297242144,"remaining_time":0.5612709565},
{"learn":[3.522813541],"iteration":698,"passed_time":1.298048112,"remaining_time":0.5589592014},
{"learn":[3.519148203],"iteration":699,"passed_time":1.298845121,"remaining_time":0.5566479091},
{"learn":[3.517236747],"iteration":700,"passed_time":1.299648187,"remaining_time":0.5543435205},
{"learn":[3.515603888],"iteration":701,"passed_time":1.300548266,"remaining_time":0.5520845914},
{"learn":[3.51263524],"iteration":702,"passed_time":1.301394937,"remaining_time":0.5498069651},
{"learn":[3.51123442],"iteration":703,"passed_time":1.302198921,"remaining_time":0.5475154553},
{"learn":[3.50828027],"iteration":704,"passed_time":1.303009475,"remaining_time":0.545230915},
{"learn":[3.508265537],"iteration":705,"passed_time":1.303500796,"remaining_time":0.542817612},
{"learn":[3.506774876],"iteration":706,"passed_time":1.304493225,"remaining_time":0.5406174184},
{"learn":[3.50552068],"iteration":707,"passed_time":1.305264602,"remaining_time":0.5383294685},
{"learn":[3.501973993],"iteration":708,"passed_time":1.306104816,"remaining_time":0.5360740502},
{"learn":[3.498880354],"iteration":709,"passed_time":1.30689238,"remaining_time":0.5338011131},
{"learn":[3.497370959],"iteration":710,"passed_time":1.307672046,"remaining_time":0.5315291438},
{"learn":[3.496050455],"iteration":711,"passed_time":1.3085095,"remaining_time":0.5292847414},
{"learn":[3.495630067],"iteration":712,"passed_time":1.309302604,"remaining_time":0.5270264337},
{"learn":[3.49550669],"iteration":713,"passed_time":1.310114949,"remaining_time":0.5247799377},
{"learn":[3.493652375],"iteration":714,"passed_time":1.310923702,"remaining_time":0.5225360212},
{"learn":[3.491915684],"iteration":715,"passed_time":1.311764208,"remaining_time":0.5203087082},
{"learn":[3.490303956],"iteration":716,"passed_time":1.312573699,"remaining_time":0.518073022},
{"learn":[3.488363853],"iteration":717,"passed_time":1.313378311,"remaining_time":0.5158393924},
{"learn":[3.485483936],"iteration":718,"passed_time":1.314187002,"remaining_time":0.5136113316},
{"learn":[3.483763466],"iteration":719,"passed_time":1.315060422,"remaining_time":0.5114123865},
{"learn":[3.481642352],"iteration":720,"passed_time":1.315881764,"remaining_time":0.5091969655},
{"learn":[3.479826119],"iteration":721,"passed_time":1.316712851,"remaining_time":0.5069891587},
{"learn":[3.478588728],"iteration":722,"passed_time":1.317471489,"remaining_time":0.5047574031},
{"learn":[3.475390887],"iteration":723,"passed_time":1.318635673,"remaining_time":0.5026843173},
{"learn":[3.472636852],"iteration":724,"passed_time":1.319481817,"remaining_time":0.5004931032},
{"learn":[3.47061883],"iteration":725,"passed_time":1.320286014,"remaining_time":0.498289763},
{"learn":[3.46953149],"iteration":726,"passed_time":1.321079401,"remaining_time":0.4960862123},
{"learn":[3.467217162],"iteration":727,"passed_time":1.321881948,"remaining_time":0.4938899585},
{"learn":[3.465686216],"iteration":728,"passed_time":1.322731908,"remaining_time":0.4917151537},
{"learn":[3.462631216],"iteration":729,"passed_time":1.323525693,"remaining_time":0.4895232016},
{"learn":[3.461451053],"iteration":730,"passed_time":1.324378153,"remaining_time":0.4873566663},
{"learn":[3.458950469],"iteration":731,"passed_time":1.325205169,"remaining_time":0.4851844061},
{"learn":[3.458072145],"iteration":732,"passed_time":1.326018396,"remaining_time":0.4830107936},
{"learn":[3.454364268],"iteration":733,"passed_time":1.326839485,"remaining_time":0.4808437369},
{"learn":[3.453243406],"iteration":734,"passed_time":1.327704913,"remaining_time":0.4786963292},
{"learn":[3.453017963],"iteration":735,"passed_time":1.32849996,"remaining_time":0.4765271596},
{"learn":[3.45201581],"iteration":736,"passed_time":1.329330798,"remaining_time":0.4743744911},
{"learn":[3.449510107],"iteration":737,"passed_time":1.330151435,"remaining_time":0.4722217832},
{"learn":[3.447189189],"iteration":738,"passed_time":1.330965676,"remaining_time":0.4700704215},
{"learn":[3.446423605],"iteration":739,"passed_time":1.331765987,"remaining_time":0.4679177791},
{"learn":[3.445531987],"iteration":740,"passed_time":1.332997379,"remaining_time":0.4659194619},
{"learn":[3.445328199],"iteration":741,"passed_time":1.333965584,"remaining_time":0.4638316991},
{"learn":[3.443327544],"iteration":742,"passed_time":1.335012448,"remaining_time":0.4617741576},
{"learn":[3.441475798],"iteration":743,"passed_time":1.336663881,"remaining_time":0.4599273568},
{"learn":[3.439046501],"iteration":744,"passed_time":1.338155529,"remaining_time":0.4580263893},
{"learn":[3.435899469],"iteration":745,"passed_time":1.339416225,"remaining_time":0.4560478835},
{"learn":[3.433988352],"iteration":746,"passed_time":1.340517522,"remaining_time":0.4540173132},
{"learn":[3.433413263],"iteration":747,"passed_time":1.341317979,"remaining_time":0.4518878753},
{"learn":[3.429944699],"iteration":748,"passed_time":1.342114609,"remaining_time":0.4497607035},
{"learn":[3.429291634],"iteration":749,"passed_time":1.343265252,"remaining_time":0.4477550841},
{"learn":[3.429175603],"iteration":750,"passed_time":1.344204033,"remaining_time":0.445681497},
{"learn":[3.428780323],"iteration":751,"passed_time":1.345554791,"remaining_time":0.4437467926},
{"learn":[3.423893341],"iteration":752,"passed_time":1.346436973,"remaining_time":0.4416599366},
{"learn":[3.421024316],"iteration":753,"passed_time":1.347248201,"remaining_time":0.4395531266},
{"learn":[3.420969872],"iteration":754,"passed_time":1.348000929,"remaining_time":0.437430765},
{"learn":[3.419544785],"iteration":755,"passed_time":1.34877158,"remaining_time":0.4353178114},
{"learn":[3.417057977],"iteration":756,"passed_time":1.349550286,"remaining_time":0.4332109899},
{"learn":[3.415160245],"iteration":757,"passed_time":1.350365285,"remaining_time":0.4311192598},
{"learn":[3.412854597],"iteration":758,"passed_time":1.351148939,"remaining_time":0.429020941},
{"learn":[3.410926347],"iteration":759,"passed_time":1.351923126,"remaining_time":0.4269230923},
{"learn":[3.408963843],"iteration":760,"passed_time":1.352776285,"remaining_time":0.4248535245},
{"learn":[3.407629634],"iteration":761,"passed_time":1.353645816,"remaining_time":0.4227922627},
{"learn":[3.404384724],"iteration":762,"passed_time":1.354438994,"remaining_time":0.4207104084},
{"learn":[3.403041656],"iteration":763,"passed_time":1.355329717,"remaining_time":0.4186620593},
{"learn":[3.401101731],"iteration":764,"passed_time":1.356185082,"remaining_time":0.4166058749},
{"learn":[3.400890668],"iteration":765,"passed_time":1.356970013,"remaining_time":0.4145313096},
{"learn":[3.399289941],"iteration":766,"passed_time":1.358293675,"remaining_time":0.4126237632},
{"learn":[3.399202366],"iteration":767,"passed_time":1.359495418,"remaining_time":0.4106809076},
{"learn":[3.397447845],"iteration":768,"passed_time":1.360356246,"remaining_time":0.4086375719},
{"learn":[3.394655341],"iteration":769,"passed_time":1.361169214,"remaining_time":0.4065830119},
{"learn":[3.393228229],"iteration":770,"passed_time":1.36193721,"remaining_time":0.4045183154},
{"learn":[3.389691197],"iteration":771,"passed_time":1.362731969,"remaining_time":0.4024648822},
{"learn":[3.389626772],"iteration":772,"passed_time":1.363440107,"remaining_time":0.4003892682},
{"learn":[3.388480222],"iteration":773,"passed_time":1.364219527,"remaining_time":0.3983380013},
{"learn":[3.388215066],"iteration":774,"passed_time":1.365057747,"remaining_time":0.3963070878},
{"learn":[3.386324358],"iteration":775,"passed_time":1.365876148,"remaining_time":0.3942735272},
{"learn":[3.383913061],"iteration":776,"passed_time":1.366687346,"remaining_time":0.3922410271},
{"learn":[3.382839768],"iteration":777,"passed_time":1.367480574,"remaining_time":0.3902065391},
{"learn":[3.381961844],"iteration":778,"passed_time":1.368304989,"remaining_time":0.3881840853},
{"learn":[3.381521703],"iteration":779,"passed_time":1.369086735,"remaining_time":0.386152669},
{"learn":[3.380918963],"iteration":780,"passed_time":1.36987182,"remaining_time":0.3841253887},
{"learn":[3.377139006],"iteration":781,"passed_time":1.370698492,"remaining_time":0.3821128789},
{"learn":[3.376004372],"iteration":782,"passed_time":1.371475906,"remaining_time":0.3800897467},
{"learn":[3.373826468],"iteration":783,"passed_time":1.372485821,"remaining_time":0.3781338486},
{"learn":[3.373546786],"iteration":784,"passed_time":1.373901499,"remaining_time":0.3762914933},
{"learn":[3.372109181],"iteration":785,"passed_time":1.375008694,"remaining_time":0.3743662347},
{"learn":[3.370764924],"iteration":786,"passed_time":1.376131658,"remaining_time":0.3724473229},
{"learn":[3.367833107],"iteration":787,"passed_time":1.376969315,"remaining_time":0.3704536736},
{"learn":[3.36450404],"iteration":788,"passed_time":1.377803772,"remaining_time":0.3684620986},
{"learn":[3.361794558],"iteration":789,"passed_time":1.37864762,"remaining_time":0.3664759497},
{"learn":[3.356880529],"iteration":790,"passed_time":1.379477575,"remaining_time":0.3644890178},
{"learn":[3.353843509],"iteration":791,"passed_time":1.380327827,"remaining_time":0.3625103383},
{"learn":[3.353640253],"iteration":792,"passed_time":1.381105979,"remaining_time":0.3605156843},
{"learn":[3.353055088],"iteration":793,"passed_time":1.381884429,"remaining_time":0.3585241718},
{"learn":[3.351415617],"iteration":794,"passed_time":1.382715376,"remaining_time":0.356549248},
{"learn":[3.349169061],"iteration":795,"passed_time":1.38347551,"remaining_time":0.3545590502},
{"learn":[3.346211014],"iteration":796,"passed_time":1.384302193,"remaining_time":0.3525888897},
{"learn":[3.344560452],"iteration":797,"passed_time":1.385280205,"remaining_time":0.3506599016},
{"learn":[3.344445461],"iteration":798,"passed_time":1.386088751,"remaining_time":0.3486906619},
{"learn":[3.342608898],"iteration":799,"passed_time":1.387378071,"remaining_time":0.3468445178},
{"learn":[3.339572899],"iteration":800,"passed_time":1.388548183,"remaining_time":0.3449701478},
{"learn":[3.339309302],"iteration":801,"passed_time":1.38947097,"remaining_time":0.3430364738},
{"learn":[3.33698088],"iteration":802,"passed_time":1.390894037,"remaining_time":0.3412280513},
{"learn":[3.334746342],"iteration":803,"passed_time":1.393045555,"remaining_time":0.3395981702},
{"learn":[3.332048511],"iteration":804,"passed_time":1.393876773,"remaining_time":0.3376471685},
{"learn":[3.331932544],"iteration":805,"passed_time":1.394647836,"remaining_time":0.3356844666},
{"learn":[3.330541133],"iteration":806,"passed_time":1.395431111,"remaining_time":0.3337276388},
{"learn":[3.329124989],"iteration":807,"passed_time":1.396273392,"remaining_time":0.3317877367},
{"learn":[3.32583918],"iteration":808,"passed_time":1.397077676,"remaining_time":0.3298415774},
{"learn":[3.325287299],"iteration":809,"passed_time":1.3978645,"remaining_time":0.3278941419},
{"learn":[3.322745162],"iteration":810,"passed_time":1.39863083,"remaining_time":0.3259447926},
{"learn":[3.319733662],"iteration":811,"passed_time":1.399444557,"remaining_time":0.3240093309},
{"learn":[3.318080007],"iteration":812,"passed_time":1.400274521,"remaining_time":0.3220803635},
{"learn":[3.317179538],"iteration":813,"passed_time":1.40121111,"remaining_time":0.3201784601},
{"learn":[3.315685949],"iteration":814,"passed_time":1.403294236,"remaining_time":0.3185391824},
{"learn":[3.314944576],"iteration":815,"passed_time":1.404413794,"remaining_time":0.3166815419},
{"learn":[3.312369052],"iteration":816,"passed_time":1.405243919,"remaining_time":0.3147608779},
{"learn":[3.312321621],"iteration":817,"passed_time":1.405833463,"remaining_time":0.3127893523},
{"learn":[3.309465776],"iteration":818,"passed_time":1.40663975,"remaining_time":0.3108691022},
{"learn":[3.308307377],"iteration":819,"passed_time":1.407423482,"remaining_time":0.3089466179},
{"learn":[3.308076804],"iteration":820,"passed_time":1.408169483,"remaining_time":0.3070186814},
{"learn":[3.305643326],"iteration":821,"passed_time":1.408985462,"remaining_time":0.3051087741},
{"learn":[3.304154814],"iteration":822,"passed_time":1.409762691,"remaining_time":0.3031931911},
{"learn":[3.303076321],"iteration":823,"passed_time":1.41054012,"remaining_time":0.301280414},
{"learn":[3.301746372],"iteration":824,"passed_time":1.41129666,"remaining_time":0.2993659583},
{"learn":[3.301345455],"iteration":825,"passed_time":1.412064965,"remaining_time":0.2974567845},
{"learn":[3.299181039],"iteration":826,"passed_time":1.412838918,"remaining_time":0.2955515512},
{"learn":[3.297989357],"iteration":827,"passed_time":1.413712254,"remaining_time":0.2936696953},
{"learn":[3.294775182],"iteration":828,"passed_time":1.414876872,"remaining_time":0.2918503559},
{"learn":[3.293840636],"iteration":829,"passed_time":1.4157502,"remaining_time":0.2899729326},
{"learn":[3.289279397],"iteration":830,"passed_time":1.416902399,"remaining_time":0.2881546396},
{"learn":[3.286204979],"iteration":831,"passed_time":1.418021035,"remaining_time":0.2863311704},
{"learn":[3.284833593],"iteration":832,"passed_time":1.419546048,"remaining_time":0.2845908644},
{"learn":[3.283519914],"iteration":833,"passed_time":1.420389919,"remaining_time":0.2827154995},
{"learn":[3.282853026],"iteration":834,"passed_time":1.421199881,"remaining_time":0.2808359047},
{"learn":[3.281944673],"iteration":835,"passed_time":1.42206793,"remaining_time":0.2789702638},
{"learn":[3.279764865],"iteration":836,"passed_time":1.422902953,"remaining_time":0.277100575},
{"learn":[3.277468839],"iteration":837,"passed_time":1.423688348,"remaining_time":0.2752237618},
{"learn":[3.277124974],"iteration":838,"passed_time":1.424496145,"remaining_time":0.2733538491},
{"learn":[3.275636037],"iteration":839,"passed_time":1.425299203,"remaining_time":0.2714855624},
{"learn":[3.274413635],"iteration":840,"passed_time":1.426144895,"remaining_time":0.2696278696},
{"learn":[3.272636087],"iteration":841,"passed_time":1.426926291,"remaining_time":0.2677605154},
{"learn":[3.269644466],"iteration":842,"passed_time":1.427730075,"remaining_time":0.2658999072},
{"learn":[3.26852083],"iteration":843,"passed_time":1.428925808,"remaining_time":0.2641142488},
{"learn":[3.267820927],"iteration":844,"passed_time":1.429962083,"remaining_time":0.2623007371},
{"learn":[3.267331099],"iteration":845,"passed_time":1.430841427,"remaining_time":0.2604604963},
{"learn":[3.267231014],"iteration":846,"passed_time":1.4318957,"remaining_time":0.2586541229},
{"learn":[3.267158695],"iteration":847,"passed_time":1.433295129,"remaining_time":0.256911391},
{"learn":[3.264718705],"iteration":848,"passed_time":1.434173215,"remaining_time":0.2550767438},
{"learn":[3.261678512],"iteration":849,"passed_time":1.435013779,"remaining_time":0.2532377257},
{"learn":[3.261368381],"iteration":850,"passed_time":1.435802866,"remaining_time":0.2513920412},
{"learn":[3.260128799],"iteration":851,"passed_time":1.436576239,"remaining_time":0.2495461072},
{"learn":[3.258972952],"iteration":852,"passed_time":1.437378608,"remaining_time":0.247707685},
{"learn":[3.258724846],"iteration":853,"passed_time":1.438173177,"remaining_time":0.2458703558},
{"learn":[3.25686724],"iteration":854,"passed_time":1.438987493,"remaining_time":0.2440388147},
{"learn":[3.255750259],"iteration":855,"passed_time":1.439746462,"remaining_time":0.2422003394},
{"learn":[3.254915866],"iteration":856,"passed_time":1.440637434,"remaining_time":0.2403864096},
{"learn":[3.254348625],"iteration":857,"passed_time":1.44141409,"remaining_time":0.2385557118},
{"learn":[3.253408514],"iteration":858,"passed_time":1.443111943,"remaining_time":0.2368786774},
{"learn":[3.253291714],"iteration":859,"passed_time":1.444182537,"remaining_time":0.2350994828},
{"learn":[3.250186342],"iteration":860,"passed_time":1.445258088,"remaining_time":0.2333227342},
{"learn":[3.249141318],"iteration":861,"passed_time":1.446170036,"remaining_time":0.2315214211},
{"learn":[3.246300388],"iteration":862,"passed_time":1.446997106,"remaining_time":0.2297086947},
{"learn":[3.245205135],"iteration":863,"passed_time":1.447947139,"remaining_time":0.2279176052},
{"learn":[3.244403535],"iteration":864,"passed_time":1.448832745,"remaining_time":0.2261184052},
{"learn":[3.244211781],"iteration":865,"passed_time":1.449692425,"remaining_time":0.2243173036},
{"learn":[3.242286347],"iteration":866,"passed_time":1.450491351,"remaining_time":0.2225090538},
{"learn":[3.239606746],"iteration":867,"passed_time":1.451309861,"remaining_time":0.2207061079},
{"learn":[3.236773361],"iteration":868,"passed_time":1.452125994,"remaining_time":0.2189050693},
{"learn":[3.234552446],"iteration":869,"passed_time":1.452924538,"remaining_time":0.2171036666},
{"learn":[3.233724647],"iteration":870,"passed_time":1.4537388,"remaining_time":0.2153068946},
{"learn":[3.230851485],"iteration":871,"passed_time":1.454516524,"remaining_time":0.2135070128},
{"learn":[3.227728941],"iteration":872,"passed_time":1.45540348,"remaining_time":0.2117253631},
{"learn":[3.225787575],"iteration":873,"passed_time":1.45685446,"remaining_time":0.2100270731},
{"learn":[3.222797487],"iteration":874,"passed_time":1.457817511,"remaining_time":0.2082596444},
{"learn":[3.22137014],"iteration":875,"passed_time":1.458658991,"remaining_time":0.2064768435},
{"learn":[3.219701963],"iteration":876,"passed_time":1.459474925,"remaining_time":0.2046926063},
{"learn":[3.21783327],"iteration":877,"passed_time":1.460307962,"remaining_time":0.2029129515},
{"learn":[3.217713355],"iteration":878,"passed_time":1.461278806,"remaining_time":0.2011544204},
{"learn":[3.217666091],"iteration":879,"passed_time":1.462668876,"remaining_time":0.1994548467},
{"learn":[3.214962005],"iteration":880,"passed_time":1.463605405,"remaining_time":0.1976947142},
{"learn":[3.214081828],"iteration":881,"passed_time":1.464381344,"remaining_time":0.1959149645},
{"learn":[3.213358337],"iteration":882,"passed_time":1.465161194,"remaining_time":0.1941380064},
{"learn":[3.210850401],"iteration":883,"passed_time":1.465970244,"remaining_time":0.192367136},
{"learn":[3.207810328],"iteration":884,"passed_time":1.466764581,"remaining_time":0.1905965275},
{"learn":[3.204935073],"iteration":885,"passed_time":1.467553162,"remaining_time":0.188827382},
{"learn":[3.20280198],"iteration":886,"passed_time":1.468327439,"remaining_time":0.1870586252},
{"learn":[3.200663495],"iteration":887,"passed_time":1.469384785,"remaining_time":0.1853278108},
{"learn":[3.197301669],"iteration":888,"passed_time":1.470523963,"remaining_time":0.1836087288},
{"learn":[3.195666943],"iteration":889,"passed_time":1.471602213,"remaining_time":0.1818834196},
{"learn":[3.193886506],"iteration":890,"passed_time":1.47244666,"remaining_time":0.1801309607},
{"learn":[3.190601248],"iteration":891,"passed_time":1.473230794,"remaining_time":0.1783732352},
{"learn":[3.188983797],"iteration":892,"passed_time":1.474086722,"remaining_time":0.1766262926},
{"learn":[3.187365749],"iteration":893,"passed_time":1.474966139,"remaining_time":0.1748841284},
{"learn":[3.186160771],"iteration":894,"passed_time":1.475776094,"remaining_time":0.1731357429},
{"learn":[3.185358981],"iteration":895,"passed_time":1.476553549,"remaining_time":0.1713856797},
{"learn":[3.183832164],"iteration":896,"passed_time":1.477351399,"remaining_time":0.1696401272},
{"learn":[3.183106966],"iteration":897,"passed_time":1.478154942,"remaining_time":0.1678973319},
{"learn":[3.182838152],"iteration":898,"passed_time":1.47899025,"remaining_time":0.1661601949},
{"learn":[3.180835453],"iteration":899,"passed_time":1.479813462,"remaining_time":0.164423718},
{"learn":[3.179957348],"iteration":900,"passed_time":1.480666284,"remaining_time":0.1626925218},
{"learn":[3.179752966],"iteration":901,"passed_time":1.481491504,"remaining_time":0.1609602743},
{"learn":[3.178851983],"iteration":902,"passed_time":1.482418963,"remaining_time":0.1592410182},
{"learn":[3.176748586],"iteration":903,"passed_time":1.483672022,"remaining_time":0.1575580908},
{"learn":[3.172960988],"iteration":904,"passed_time":1.484718854,"remaining_time":0.1558544654},
{"learn":[3.172794225],"iteration":905,"passed_time":1.485733177,"remaining_time":0.1541489168},
{"learn":[3.169996507],"iteration":906,"passed_time":1.486789144,"remaining_time":0.1524491625},
{"learn":[3.16813015],"iteration":907,"passed_time":1.487752798,"remaining_time":0.150741473},
{"learn":[3.166920871],"iteration":908,"passed_time":1.488897876,"remaining_time":0.1490535828},
{"learn":[3.16531606],"iteration":909,"passed_time":1.490170415,"remaining_time":0.1473794915},
{"learn":[3.162035247],"iteration":910,"passed_time":1.491617174,"remaining_time":0.1457233024},
{"learn":[3.16189467],"iteration":911,"passed_time":1.492830679,"remaining_time":0.1440450655},
{"learn":[3.161008416],"iteration":912,"passed_time":1.493822679,"remaining_time":0.1423467394},
{"learn":[3.160560787],"iteration":913,"passed_time":1.494856879,"remaining_time":0.1406539296},
{"learn":[3.160416261],"iteration":914,"passed_time":1.496842625,"remaining_time":0.1390509542},
{"learn":[3.15844291],"iteration":915,"passed_time":1.498275199,"remaining_time":0.1373964156},
{"learn":[3.155040501],"iteration":916,"passed_time":1.499129069,"remaining_time":0.1356899811},
{"learn":[3.154937548],"iteration":917,"passed_time":1.499925342,"remaining_time":0.1339802593},
{"learn":[3.153721161],"iteration":918,"passed_time":1.500734374,"remaining_time":0.1322736499},
{"learn":[3.153170511],"iteration":919,"passed_time":1.501500917,"remaining_time":0.1305652971},
{"learn":[3.153113601],"iteration":920,"passed_time":1.502311845,"remaining_time":0.1288627967},
{"learn":[3.150607379],"iteration":921,"passed_time":1.503078964,"remaining_time":0.1271585241},
{"learn":[3.148408359],"iteration":922,"passed_time":1.5039289,"remaining_time":0.125463191},
{"learn":[3.147495728],"iteration":923,"passed_time":1.505132613,"remaining_time":0.1237987863},
{"learn":[3.146946235],"iteration":924,"passed_time":1.506118361,"remaining_time":0.1221177049},
{"learn":[3.14472738],"iteration":925,"passed_time":1.50712197,"remaining_time":0.1204395527},
{"learn":[3.144469477],"iteration":926,"passed_time":1.508375073,"remaining_time":0.1187825031},
{"learn":[3.142975516],"iteration":927,"passed_time":1.510486445,"remaining_time":0.1171929138},
{"learn":[3.14079113],"iteration":928,"passed_time":1.51134371,"remaining_time":0.1155063546},
{"learn":[3.138173032],"iteration":929,"passed_time":1.512163789,"remaining_time":0.1138187799},
{"learn":[3.136352813],"iteration":930,"passed_time":1.512980251,"remaining_time":0.1121328006},
{"learn":[3.133735004],"iteration":931,"passed_time":1.513833129,"remaining_time":0.1104513442},
{"learn":[3.1319496],"iteration":932,"passed_time":1.514653952,"remaining_time":0.108769362},
{"learn":[3.129865343],"iteration":933,"passed_time":1.515486306,"remaining_time":0.1070900387},
{"learn":[3.129830206],"iteration":934,"passed_time":1.516067859,"remaining_time":0.1053950918},
{"learn":[3.126676562],"iteration":935,"passed_time":1.516844084,"remaining_time":0.1037158348},
{"learn":[3.12645665],"iteration":936,"passed_time":1.517608986,"remaining_time":0.102037744},
{"learn":[3.126378007],"iteration":937,"passed_time":1.518366571,"remaining_time":0.1003611166},
{"learn":[3.124621914],"iteration":938,"passed_time":1.519385773,"remaining_time":0.09870344213},
{"learn":[3.123379018],"iteration":939,"passed_time":1.520472213,"remaining_time":0.09705141783},
{"learn":[3.123332451],"iteration":940,"passed_time":1.521673011,"remaining_time":0.0954077658},
{"learn":[3.122432444],"iteration":941,"passed_time":1.522581043,"remaining_time":0.09374702815},
{"learn":[3.121889006],"iteration":942,"passed_time":1.523517423,"remaining_time":0.09208960033},
{"learn":[3.121070914],"iteration":943,"passed_time":1.524342071,"remaining_time":0.090427072},
{"learn":[3.118444705],"iteration":944,"passed_time":1.52514756,"remaining_time":0.08876520189},
{"learn":[3.116820458],"iteration":945,"passed_time":1.52596766,"remaining_time":0.08710597638},
{"learn":[3.114971041],"iteration":946,"passed_time":1.526803239,"remaining_time":0.08544938929},
{"learn":[3.114685138],"iteration":947,"passed_time":1.52759646,"remaining_time":0.08379221089},
{"learn":[3.113399363],"iteration":948,"passed_time":1.528408699,"remaining_time":0.08213787531},
{"learn":[3.110575399],"iteration":949,"passed_time":1.529222617,"remaining_time":0.0804854009},
{"learn":[3.110466553],"iteration":950,"passed_time":1.529989712,"remaining_time":0.07883227749},
{"learn":[3.108691641],"iteration":951,"passed_time":1.530789623,"remaining_time":0.07718267008},
{"learn":[3.107898017],"iteration":952,"passed_time":1.531578555,"remaining_time":0.0755343044},
{"learn":[3.105551729],"iteration":953,"passed_time":1.532445863,"remaining_time":0.0738915196},
{"learn":[3.104824945],"iteration":954,"passed_time":1.533220862,"remaining_time":0.07224600921},
{"learn":[3.103186704],"iteration":955,"passed_time":1.534165258,"remaining_time":0.07061011648},
{"learn":[3.102330655],"iteration":956,"passed_time":1.534939175,"remaining_time":0.06896800892},
{"learn":[3.102291298],"iteration":957,"passed_time":1.535713587,"remaining_time":0.06732773556},
{"learn":[3.100363529],"iteration":958,"passed_time":1.537184003,"remaining_time":0.06571902409},
{"learn":[3.097871596],"iteration":959,"passed_time":1.538023973,"remaining_time":0.06408433222},
{"learn":[3.097372213],"iteration":960,"passed_time":1.538843228,"remaining_time":0.06245045358},
{"learn":[3.095981813],"iteration":961,"passed_time":1.539665962,"remaining_time":0.06081840597},
{"learn":[3.095347452],"iteration":962,"passed_time":1.540625828,"remaining_time":0.05919330801},
{"learn":[3.094728409],"iteration":963,"passed_time":1.54148197,"remaining_time":0.05756571672},
{"learn":[3.094118537],"iteration":964,"passed_time":1.542284813,"remaining_time":0.05593779113},
{"learn":[3.093793695],"iteration":965,"passed_time":1.543061004,"remaining_time":0.05431063574},
{"learn":[3.092581602],"iteration":966,"passed_time":1.54395722,"remaining_time":0.05268933636},
{"learn":[3.091694202],"iteration":967,"passed_time":1.544924014,"remaining_time":0.05107186824},
{"learn":[3.090298312],"iteration":968,"passed_time":1.545778307,"remaining_time":0.04945214399},
{"learn":[3.090020107],"iteration":969,"passed_time":1.546573786,"remaining_time":0.04783217895},
{"learn":[3.088949869],"iteration":970,"passed_time":1.54733968,"remaining_time":0.04621302855},
{"learn":[3.086700204],"iteration":971,"passed_time":1.54811505,"remaining_time":0.0445959068},
{"learn":[3.086584317],"iteration":972,"passed_time":1.548887741,"remaining_time":0.04298044092},
{"learn":[3.084850742],"iteration":973,"passed_time":1.549699064,"remaining_time":0.04136773681},
{"learn":[3.084239948],"iteration":974,"passed_time":1.550853757,"remaining_time":0.03976548094},
{"learn":[3.082561673],"iteration":975,"passed_time":1.55165996,"remaining_time":0.03815557278},
{"learn":[3.07991814],"iteration":976,"passed_time":1.552479987,"remaining_time":0.03654763531},
{"learn":[3.079350277],"iteration":977,"passed_time":1.553264481,"remaining_time":0.0349405098},
{"learn":[3.077637462],"iteration":978,"passed_time":1.554139278,"remaining_time":0.03333700187},
{"learn":[3.076733301],"iteration":979,"passed_time":1.554938874,"remaining_time":0.03173344641},
{"learn":[3.07594065],"iteration":980,"passed_time":1.555755633,"remaining_time":0.03013186241},
{"learn":[3.072594655],"iteration":981,"passed_time":1.556545928,"remaining_time":0.02853139176},
{"learn":[3.071977674],"iteration":982,"passed_time":1.557342351,"remaining_time":0.02693267546},
{"learn":[3.069532634],"iteration":983,"passed_time":1.558150975,"remaining_time":0.02533578821},
{"learn":[3.068870784],"iteration":984,"passed_time":1.558936837,"remaining_time":0.02374015488},
{"learn":[3.068801463],"iteration":985,"passed_time":1.559696147,"remaining_time":0.02214578708},
{"learn":[3.067433249],"iteration":986,"passed_time":1.560517583,"remaining_time":0.02055392967},
{"learn":[3.065611456],"iteration":987,"passed_time":1.561332372,"remaining_time":0.01896355107},
{"learn":[3.063039162],"iteration":988,"passed_time":1.562126542,"remaining_time":0.01737451159},
{"learn":[3.06177873],"iteration":989,"passed_time":1.56293439,"remaining_time":0.01578721606},
{"learn":[3.061689148],"iteration":990,"passed_time":1.564199706,"remaining_time":0.01420564819},
{"learn":[3.058984039],"iteration":991,"passed_time":1.565249348,"remaining_time":0.01262297861},
{"learn":[3.057492984],"iteration":992,"passed_time":1.566314308,"remaining_time":0.01104149059},
{"learn":[3.057290731],"iteration":993,"passed_time":1.567084986,"remaining_time":0.009459265508},
{"learn":[3.056068348],"iteration":994,"passed_time":1.567851866,"remaining_time":0.007878652592},
{"learn":[3.054987307],"iteration":995,"passed_time":1.568664117,"remaining_time":0.00629985589},
{"learn":[3.054200234],"iteration":996,"passed_time":1.569449391,"remaining_time":0.004722515719},
{"learn":[3.052732869],"iteration":997,"passed_time":1.570261091,"remaining_time":0.003146815814},
{"learn":[3.051787862],"iteration":998,"passed_time":1.571029143,"remaining_time":0.001572601745},
{"learn":[3.051366222],"iteration":999,"passed_time":1.57184921,"remaining_time":0}
]}